{
  "Albania": {
    "x": "2020-01-01 00:00:00",
    "y": 2.727098410237434,
    "yr": "2020-01-01",
    "c": "Albania",
    "o": 3.0,
    "o2": 0.0,
    "color": "black",
    "x0": 0.6714897339863479,
    "x0_raw": 0.6714897339863479,
    "A": 1.0400621408083086,
    "r2N": 3.1201864224249256,
    "max_s": 3.0,
    "delta_t": 0.0,
    "phase": "Deactivated"
  },
  "Algeria": {
    "x": "2020-01-01 00:00:00",
    "y": 2.9444739361128938,
    "yr": "2020-01-01",
    "c": "Algeria",
    "o": 5.0,
    "o2": 0.0,
    "color": "black",
    "x0": 0.6153376658951845,
    "x0_raw": 0.6153376658951845,
    "A": 1.0138323697425207,
    "r2N": 5.069161848712604,
    "max_s": 5.0,
    "delta_t": 0.0,
    "phase": "Deactivated"
  },
  "Argentina": {
    "x": "2016-02-25 00:00:00",
    "y": 2.682967827246665,
    "yr": "2020-01-01",
    "c": "Argentina",
    "o": 11.0,
    "o2": 0.0,
    "color": "red",
    "x0": 0.7039387062582705,
    "x0_raw": 0.7039387062582705,
    "A": 1.0671812814533481,
    "r2N": 11.738994095986829,
    "max_s": 11.0,
    "delta_t": 7.805555555555555,
    "phase": "Deceleration"
  },
  "Australia": {
    "x": "2014-03-07 00:00:00",
    "y": 2.0852742100716193,
    "yr": "2020-01-01",
    "c": "Australia",
    "o": 325.0,
    "o2": 0.0,
    "color": "red",
    "x0": 0.5523146360378604,
    "x0_raw": 0.5523146360378604,
    "A": 1.0675558442116901,
    "r2N": 346.9556493687993,
    "max_s": 325.0,
    "delta_t": 11.805555555555555,
    "phase": "Deceleration"
  },
  "Austria": {
    "x": "2014-12-18 00:00:00",
    "y": 2.0437075757115837,
    "yr": "2020-01-01",
    "c": "Austria",
    "o": 52.0,
    "o2": 0.0,
    "color": "red",
    "x0": 0.6125765338274074,
    "x0_raw": 0.6125765338274074,
    "A": 1.1113157766349473,
    "r2N": 57.78842038501726,
    "max_s": 52.0,
    "delta_t": 10.216666666666667,
    "phase": "Deceleration"
  },
  "Bangladesh": {
    "x": "2015-06-13 00:00:00",
    "y": 2.3233813697233177,
    "yr": "2020-01-01",
    "c": "Bangladesh",
    "o": 7.0,
    "o2": 0.0,
    "color": "red",
    "x0": 0.6498239011577207,
    "x0_raw": 0.6498239011577207,
    "A": 1.0915120420979252,
    "r2N": 7.6405842946854765,
    "max_s": 7.0,
    "delta_t": 9.233333333333333,
    "phase": "Deceleration"
  },
  "Belgium": {
    "x": "2020-01-01 00:00:00",
    "y": 2.210608560224297,
    "yr": "2020-01-01",
    "c": "Belgium",
    "o": 73.0,
    "o2": 0.0,
    "color": "black",
    "x0": 0.5380940748763562,
    "x0_raw": 0.5380940748763562,
    "A": 1.0318383801551054,
    "r2N": 75.32420175132269,
    "max_s": 73.0,
    "delta_t": 0.0,
    "phase": "Deactivated"
  },
  "Bhutan": {
    "x": "2020-01-01 00:00:00",
    "y": 8.905978135896817,
    "yr": "2020-01-01",
    "c": "Bhutan",
    "o": 1.0,
    "o2": 0.0,
    "color": "black",
    "x0": 0.7803073567284607,
    "x0_raw": 0.7803073567284607,
    "A": 0.9999999999999776,
    "r2N": 0.9999999999999776,
    "max_s": 1.0,
    "delta_t": 0.0,
    "phase": "Deactivated"
  },
  "Brazil": {
    "x": "2015-09-26 00:00:00",
    "y": 2.5187526080756455,
    "yr": "2020-01-01",
    "c": "Brazil",
    "o": 110.0,
    "o2": 0.0,
    "color": "red",
    "x0": 0.6719326284499982,
    "x0_raw": 0.6719326284499982,
    "A": 1.0691819656197106,
    "r2N": 117.61001621816817,
    "max_s": 110.0,
    "delta_t": 8.65,
    "phase": "Deceleration"
  },
  "Bulgaria": {
    "x": "2020-01-01 00:00:00",
    "y": 8.933505637394735,
    "yr": "2020-01-01",
    "c": "Bulgaria",
    "o": 1.0,
    "o2": 0.0,
    "color": "black",
    "x0": 0.6085857027677768,
    "x0_raw": 0.6085857027677768,
    "A": 1.0000000000000153,
    "r2N": 1.0000000000000153,
    "max_s": 1.0,
    "delta_t": 0.0,
    "phase": "Deactivated"
  },
  "Burkina Faso": {
    "x": "2020-01-01 00:00:00",
    "y": 8.931687850606277,
    "yr": "2020-01-01",
    "c": "Burkina Faso",
    "o": 1.0,
    "o2": 0.0,
    "color": "black",
    "x0": 0.7651468641598889,
    "x0_raw": 0.7651468641598889,
    "A": 1.0000000000000047,
    "r2N": 1.0000000000000047,
    "max_s": 1.0,
    "delta_t": 0.0,
    "phase": "Deactivated"
  },
  "Cameroon": {
    "x": "2020-01-01 00:00:00",
    "y": 8.935947922722598,
    "yr": "2020-01-01",
    "c": "Cameroon",
    "o": 1.0,
    "o2": 0.0,
    "color": "black",
    "x0": 0.775258416729696,
    "x0_raw": 0.775258416729696,
    "A": 1.0000000000000024,
    "r2N": 1.0000000000000024,
    "max_s": 1.0,
    "delta_t": 0.0,
    "phase": "Deactivated"
  },
  "Canada": {
    "x": "2014-09-08 00:00:00",
    "y": 2.074804659802628,
    "yr": "2020-01-01",
    "c": "Canada",
    "o": 252.0,
    "o2": 0.0,
    "color": "red",
    "x0": 0.591387947935319,
    "x0_raw": 0.591387947935319,
    "A": 1.0917958605868179,
    "r2N": 275.1325568678781,
    "max_s": 252.0,
    "delta_t": 10.777777777777779,
    "phase": "Deceleration"
  },
  "Chile": {
    "x": "2014-09-21 00:00:00",
    "y": 2.272666360940844,
    "yr": "2020-01-01",
    "c": "Chile",
    "o": 33.0,
    "o2": 0.0,
    "color": "red",
    "x0": 0.5940736809025496,
    "x0_raw": 0.5940736809025496,
    "A": 1.0623756249360992,
    "r2N": 35.058395622891275,
    "max_s": 33.0,
    "delta_t": 10.705555555555556,
    "phase": "Deceleration"
  },
  "Colombia": {
    "x": "2015-03-04 00:00:00",
    "y": 2.3281980427359397,
    "yr": "2020-01-01",
    "c": "Colombia",
    "o": 40.0,
    "o2": 0.0,
    "color": "red",
    "x0": 0.6285981168985294,
    "x0_raw": 0.6285981168985294,
    "A": 1.0652195167355434,
    "r2N": 42.60878066942173,
    "max_s": 40.0,
    "delta_t": 9.794444444444444,
    "phase": "Deceleration"
  },
  "Costa Rica": {
    "x": "2020-01-01 00:00:00",
    "y": 3.5833291371216593,
    "yr": "2020-01-01",
    "c": "Costa Rica",
    "o": 2.0,
    "o2": 0.0,
    "color": "black",
    "x0": 0.7029622530203261,
    "x0_raw": 0.7029622530203261,
    "A": 1.011000026370566,
    "r2N": 2.022000052741132,
    "max_s": 2.0,
    "delta_t": 0.0,
    "phase": "Deactivated"
  },
  "Croatia": {
    "x": "2015-04-17 00:00:00",
    "y": 2.271213656310402,
    "yr": "2020-01-01",
    "c": "Croatia",
    "o": 7.0,
    "o2": 0.0,
    "color": "red",
    "x0": 0.6378680741727769,
    "x0_raw": 0.6378680741727769,
    "A": 1.0778089527145844,
    "r2N": 7.544662669002091,
    "max_s": 7.0,
    "delta_t": 9.55,
    "phase": "Deceleration"
  },
  "Cyprus": {
    "x": "2020-01-01 00:00:00",
    "y": 2.8223350238059366,
    "yr": "2020-01-01",
    "c": "Cyprus",
    "o": 6.0,
    "o2": 0.0,
    "color": "black",
    "x0": 0.6479281639725568,
    "x0_raw": 0.6479281639725568,
    "A": 1.0151392539765463,
    "r2N": 6.090835523859278,
    "max_s": 6.0,
    "delta_t": 0.0,
    "phase": "Deactivated"
  },
  "Czech Republic": {
    "x": "2015-12-21 00:00:00",
    "y": 1.9889504943191552,
    "yr": "2020-01-01",
    "c": "Czech Republic",
    "o": 36.0,
    "o2": 0.0,
    "color": "red",
    "x0": 0.6901565140713901,
    "x0_raw": 0.6901565140713901,
    "A": 1.217291429907479,
    "r2N": 43.82249147666925,
    "max_s": 36.0,
    "delta_t": 8.172222222222222,
    "phase": "Deceleration"
  },
  "Denmark": {
    "x": "2014-12-31 00:00:00",
    "y": 2.0599676846678245,
    "yr": "2020-01-01",
    "c": "Denmark",
    "o": 87.0,
    "o2": 0.0,
    "color": "red",
    "x0": 0.6154032629558815,
    "x0_raw": 0.6154032629558815,
    "A": 1.1125066381291686,
    "r2N": 96.78807751723767,
    "max_s": 87.0,
    "delta_t": 10.144444444444444,
    "phase": "Deceleration"
  },
  "Ecuador": {
    "x": "2020-01-01 00:00:00",
    "y": 3.1251772478801967,
    "yr": "2020-01-01",
    "c": "Ecuador",
    "o": 6.0,
    "o2": 0.0,
    "color": "black",
    "x0": 0.6923936755579116,
    "x0_raw": 0.6923936755579116,
    "A": 1.0192182899458813,
    "r2N": 6.115309739675288,
    "max_s": 6.0,
    "delta_t": 0.0,
    "phase": "Deactivated"
  },
  "Egypt": {
    "x": "2020-01-01 00:00:00",
    "y": 3.4854921452126764,
    "yr": "2020-01-01",
    "c": "Egypt",
    "o": 4.0,
    "o2": 0.0,
    "color": "black",
    "x0": 0.714737186683716,
    "x0_raw": 0.714737186683716,
    "A": 1.0239566749516023,
    "r2N": 4.095826699806409,
    "max_s": 4.0,
    "delta_t": 0.0,
    "phase": "Deactivated"
  },
  "Estonia": {
    "x": "2015-05-22 00:00:00",
    "y": 2.4024532023027763,
    "yr": "2020-01-01",
    "c": "Estonia",
    "o": 8.0,
    "o2": 0.0,
    "color": "red",
    "x0": 0.6453176885427225,
    "x0_raw": 0.6453176885427225,
    "A": 1.0768891869846657,
    "r2N": 8.615113495877326,
    "max_s": 8.0,
    "delta_t": 9.355555555555556,
    "phase": "Deceleration"
  },
  "Ethiopia": {
    "x": "2020-01-01 00:00:00",
    "y": 8.921742209609397,
    "yr": "2020-01-01",
    "c": "Ethiopia",
    "o": 1.0,
    "o2": 0.0,
    "color": "black",
    "x0": 0.7348499359277757,
    "x0_raw": 0.7348499359277757,
    "A": 1.000000000000009,
    "r2N": 1.000000000000009,
    "max_s": 1.0,
    "delta_t": 0.0,
    "phase": "Deactivated"
  },
  "Fiji": {
    "x": "2013-10-09 00:00:00",
    "y": 1.7039492884054455,
    "yr": "2020-01-01",
    "c": "Fiji",
    "o": 3.0,
    "o2": 0.0,
    "color": "red",
    "x0": 0.5209477025551653,
    "x0_raw": 0.5209477025551653,
    "A": 1.1761341902754745,
    "r2N": 3.5284025708264233,
    "max_s": 3.0,
    "delta_t": 12.633333333333333,
    "phase": "Deceleration"
  },
  "Finland": {
    "x": "2014-12-01 00:00:00",
    "y": 1.8722216112240677,
    "yr": "2020-01-01",
    "c": "Finland",
    "o": 94.0,
    "o2": 0.0,
    "color": "red",
    "x0": 0.609090409619112,
    "x0_raw": 0.609090409619112,
    "A": 1.1452137600949588,
    "r2N": 107.65009344892613,
    "max_s": 94.0,
    "delta_t": 10.311111111111112,
    "phase": "Deceleration"
  },
  "France": {
    "x": "2014-10-10 00:00:00",
    "y": 2.1904400042038294,
    "yr": "2020-01-01",
    "c": "France",
    "o": 121.0,
    "o2": 0.0,
    "color": "red",
    "x0": 0.5981390010744119,
    "x0_raw": 0.5981390010744119,
    "A": 1.070433647201629,
    "r2N": 129.5224713113971,
    "max_s": 121.0,
    "delta_t": 10.6,
    "phase": "Deceleration"
  },
  "Germany": {
    "x": "2014-04-23 00:00:00",
    "y": 2.1355614024171667,
    "yr": "2020-01-01",
    "c": "Germany",
    "o": 277.0,
    "o2": 0.0,
    "color": "red",
    "x0": 0.5622627440059671,
    "x0_raw": 0.5622627440059671,
    "A": 1.0622375292240123,
    "r2N": 294.2397955950514,
    "max_s": 277.0,
    "delta_t": 11.544444444444444,
    "phase": "Deceleration"
  },
  "Ghana": {
    "x": "2015-10-01 00:00:00",
    "y": 1.8842418057686856,
    "yr": "2020-01-01",
    "c": "Ghana",
    "o": 2.0,
    "o2": 0.0,
    "color": "red",
    "x0": 0.6729198535452205,
    "x0_raw": 0.6729198535452205,
    "A": 1.1714386030788395,
    "r2N": 2.342877206157679,
    "max_s": 2.0,
    "delta_t": 8.622222222222222,
    "phase": "Deceleration"
  },
  "Greece": {
    "x": "2020-01-01 00:00:00",
    "y": 2.282651707752423,
    "yr": "2020-01-01",
    "c": "Greece",
    "o": 65.0,
    "o2": 0.0,
    "color": "black",
    "x0": 0.5799438362834318,
    "x0_raw": 0.5799438362834318,
    "A": 1.048245469892429,
    "r2N": 68.1359555430079,
    "max_s": 65.0,
    "delta_t": 0.0,
    "phase": "Deactivated"
  },
  "Hungary": {
    "x": "2020-01-01 00:00:00",
    "y": 2.0623322922429317,
    "yr": "2020-01-01",
    "c": "Hungary",
    "o": 32.0,
    "o2": 0.0,
    "color": "black",
    "x0": 0.36774128102110737,
    "x0_raw": 0.36774128102110737,
    "A": 1.0116241332680531,
    "r2N": 32.3719722645777,
    "max_s": 32.0,
    "delta_t": 0.0,
    "phase": "Deactivated"
  },
  "Iceland": {
    "x": "2020-01-01 00:00:00",
    "y": 3.008902949983574,
    "yr": "2020-01-01",
    "c": "Iceland",
    "o": 6.0,
    "o2": 0.0,
    "color": "black",
    "x0": 0.712767139597915,
    "x0_raw": 0.712767139597915,
    "A": 1.0294334210030482,
    "r2N": 6.176600526018289,
    "max_s": 6.0,
    "delta_t": 0.0,
    "phase": "Deactivated"
  },
  "India": {
    "x": "2015-02-28 00:00:00",
    "y": 2.2499948079147623,
    "yr": "2020-01-01",
    "c": "India",
    "o": 319.0,
    "o2": 0.0,
    "color": "red",
    "x0": 0.6278350177916066,
    "x0_raw": 0.6278350177916066,
    "A": 1.0812896258760236,
    "r2N": 344.93139065445155,
    "max_s": 319.0,
    "delta_t": 9.816666666666666,
    "phase": "Deceleration"
  },
  "Indonesia": {
    "x": "2015-08-24 00:00:00",
    "y": 2.6222067380426934,
    "yr": "2020-01-01",
    "c": "Indonesia",
    "o": 23.0,
    "o2": 0.0,
    "color": "red",
    "x0": 0.664965166854494,
    "x0_raw": 0.664965166854494,
    "A": 1.0563358920052106,
    "r2N": 24.295725516119845,
    "max_s": 23.0,
    "delta_t": 8.833333333333334,
    "phase": "Deceleration"
  },
  "Iran": {
    "x": "2020-01-01 00:00:00",
    "y": 2.9232032571342987,
    "yr": "2020-01-01",
    "c": "Iran",
    "o": 40.0,
    "o2": 0.0,
    "color": "black",
    "x0": 0.6788273597510207,
    "x0_raw": 0.6788273597510207,
    "A": 1.029325300788605,
    "r2N": 41.1730120315442,
    "max_s": 40.0,
    "delta_t": 0.0,
    "phase": "Deactivated"
  },
  "Iraq": {
    "x": "2020-01-01 00:00:00",
    "y": 3.0854502042057357,
    "yr": "2020-01-01",
    "c": "Iraq",
    "o": 2.0,
    "o2": 0.0,
    "color": "black",
    "x0": 0.7286128859030292,
    "x0_raw": 0.7286128859030292,
    "A": 1.0281777218091654,
    "r2N": 2.056355443618331,
    "max_s": 2.0,
    "delta_t": 0.0,
    "phase": "Deactivated"
  },
  "Ireland": {
    "x": "2014-09-29 00:00:00",
    "y": 2.0756749898901727,
    "yr": "2020-01-01",
    "c": "Ireland",
    "o": 55.0,
    "o2": 0.0,
    "color": "red",
    "x0": 0.5956438658000119,
    "x0_raw": 0.5956438658000119,
    "A": 1.1069834713462894,
    "r2N": 60.884090924045914,
    "max_s": 55.0,
    "delta_t": 10.661111111111111,
    "phase": "Deceleration"
  },
  "Israel": {
    "x": "2020-01-01 00:00:00",
    "y": 2.476252082085476,
    "yr": "2020-01-01",
    "c": "Israel",
    "o": 7.0,
    "o2": 0.0,
    "color": "black",
    "x0": 0.6074968633516977,
    "x0_raw": 0.6074968633516977,
    "A": 1.049099951739394,
    "r2N": 7.343699662175758,
    "max_s": 7.0,
    "delta_t": 0.0,
    "phase": "Deactivated"
  },
  "Italy": {
    "x": "2015-01-13 00:00:00",
    "y": 2.40104161186825,
    "yr": "2020-01-01",
    "c": "Italy",
    "o": 351.0,
    "o2": 0.0,
    "color": "red",
    "x0": 0.6180639278155644,
    "x0_raw": 0.6180639278155644,
    "A": 1.0556758456569544,
    "r2N": 370.542221825591,
    "max_s": 351.0,
    "delta_t": 10.072222222222223,
    "phase": "Deceleration"
  },
  "Japan": {
    "x": "2014-12-09 00:00:00",
    "y": 1.9508584465456857,
    "yr": "2020-01-01",
    "c": "Japan",
    "o": 61.0,
    "o2": 0.0,
    "color": "red",
    "x0": 0.6106403334903016,
    "x0_raw": 0.6106403334903016,
    "A": 1.1270209686935115,
    "r2N": 68.74827909030421,
    "max_s": 61.0,
    "delta_t": 10.266666666666667,
    "phase": "Deceleration"
  },
  "Jordan": {
    "x": "2020-01-01 00:00:00",
    "y": 4.075769289332489,
    "yr": "2020-01-01",
    "c": "Jordan",
    "o": 3.0,
    "o2": 0.0,
    "color": "black",
    "x0": 0.6998968910085939,
    "x0_raw": 0.6998968910085939,
    "A": 1.0074462100839592,
    "r2N": 3.0223386302518778,
    "max_s": 3.0,
    "delta_t": 0.0,
    "phase": "Deactivated"
  },
  "Kenya": {
    "x": "2020-01-01 00:00:00",
    "y": 3.3804368177858626,
    "yr": "2020-01-01",
    "c": "Kenya",
    "o": 4.0,
    "o2": 0.0,
    "color": "black",
    "x0": 0.6570673776374462,
    "x0_raw": 0.6570673776374462,
    "A": 0.9901207027171604,
    "r2N": 3.9604828108686414,
    "max_s": 4.0,
    "delta_t": 0.0,
    "phase": "Deactivated"
  },
  "Kuwait": {
    "x": "2020-01-01 00:00:00",
    "y": 3.55047433006327,
    "yr": "2020-01-01",
    "c": "Kuwait",
    "o": 4.0,
    "o2": 0.0,
    "color": "black",
    "x0": 0.5915289977129716,
    "x0_raw": 0.5915289977129716,
    "A": 1.011755405351429,
    "r2N": 4.047021621405716,
    "max_s": 4.0,
    "delta_t": 0.0,
    "phase": "Deactivated"
  },
  "Latvia": {
    "x": "2016-02-23 00:00:00",
    "y": 1.8691241661159739,
    "yr": "2020-01-01",
    "c": "Latvia",
    "o": 6.0,
    "o2": 0.0,
    "color": "red",
    "x0": 0.7036244460713346,
    "x0_raw": 0.7036244460713346,
    "A": 1.2550744552441366,
    "r2N": 7.53044673146482,
    "max_s": 6.0,
    "delta_t": 7.816666666666666,
    "phase": "Deceleration"
  },
  "Lebanon": {
    "x": "2015-12-16 00:00:00",
    "y": 2.246736862245774,
    "yr": "2020-01-01",
    "c": "Lebanon",
    "o": 12.0,
    "o2": 0.0,
    "color": "red",
    "x0": 0.6891204006596938,
    "x0_raw": 0.6891204006596938,
    "A": 1.1309603607998246,
    "r2N": 13.571524329597896,
    "max_s": 12.0,
    "delta_t": 8.2,
    "phase": "Deceleration"
  },
  "Lithuania": {
    "x": "2015-08-17 00:00:00",
    "y": 2.1141869609592643,
    "yr": "2020-01-01",
    "c": "Lithuania",
    "o": 5.0,
    "o2": 0.0,
    "color": "red",
    "x0": 0.6636150109318872,
    "x0_raw": 0.6636150109318872,
    "A": 1.1256827302412349,
    "r2N": 5.628413651206174,
    "max_s": 5.0,
    "delta_t": 8.872222222222222,
    "phase": "Deceleration"
  },
  "Luxembourg": {
    "x": "2020-01-01 00:00:00",
    "y": 2.5075610949468414,
    "yr": "2020-01-01",
    "c": "Luxembourg",
    "o": 10.0,
    "o2": 0.0,
    "color": "black",
    "x0": 0.47587323439275875,
    "x0_raw": 0.47587323439275875,
    "A": 0.9922999968407356,
    "r2N": 9.922999968407355,
    "max_s": 10.0,
    "delta_t": 0.0,
    "phase": "Deactivated"
  },
  "Madagascar": {
    "x": "2020-01-01 00:00:00",
    "y": 8.932983152049424,
    "yr": "2020-01-01",
    "c": "Madagascar",
    "o": 1.0,
    "o2": 0.0,
    "color": "black",
    "x0": 0.603533880903608,
    "x0_raw": 0.603533880903608,
    "A": 0.9999999999999899,
    "r2N": 0.9999999999999899,
    "max_s": 1.0,
    "delta_t": 0.0,
    "phase": "Deactivated"
  },
  "Malaysia": {
    "x": "2015-02-09 00:00:00",
    "y": 2.1302264809605966,
    "yr": "2020-01-01",
    "c": "Malaysia",
    "o": 143.0,
    "o2": 0.0,
    "color": "red",
    "x0": 0.6237060357754736,
    "x0_raw": 0.6237060357754736,
    "A": 1.103480273909992,
    "r2N": 157.79767916912886,
    "max_s": 143.0,
    "delta_t": 9.922222222222222,
    "phase": "Deceleration"
  },
  "Malta": {
    "x": "2020-01-01 00:00:00",
    "y": 1.9680523187450512,
    "yr": "2020-01-01",
    "c": "Malta",
    "o": 3.0,
    "o2": 0.0,
    "color": "black",
    "x0": 0.351298129244299,
    "x0_raw": 0.351298129244299,
    "A": 0.9629706241074771,
    "r2N": 2.8889118723224314,
    "max_s": 3.0,
    "delta_t": 0.0,
    "phase": "Deactivated"
  },
  "Mauritius": {
    "x": "2020-01-01 00:00:00",
    "y": 3.121829846353852,
    "yr": "2020-01-01",
    "c": "Mauritius",
    "o": 5.0,
    "o2": 0.0,
    "color": "black",
    "x0": 0.7022071514947957,
    "x0_raw": 0.7022071514947957,
    "A": 1.0317387247543015,
    "r2N": 5.158693623771508,
    "max_s": 5.0,
    "delta_t": 0.0,
    "phase": "Deactivated"
  },
  "Mexico": {
    "x": "2015-07-30 00:00:00",
    "y": 2.5242206362921777,
    "yr": "2020-01-01",
    "c": "Mexico",
    "o": 37.0,
    "o2": 0.0,
    "color": "red",
    "x0": 0.6597245462388984,
    "x0_raw": 0.6597245462388984,
    "A": 1.0599820943148597,
    "r2N": 39.21933748964981,
    "max_s": 37.0,
    "delta_t": 8.972222222222221,
    "phase": "Deceleration"
  },
  "Morocco": {
    "x": "2020-01-01 00:00:00",
    "y": 2.958692507806801,
    "yr": "2020-01-01",
    "c": "Morocco",
    "o": 6.0,
    "o2": 0.0,
    "color": "black",
    "x0": 0.7012799698903023,
    "x0_raw": 0.7012799698903023,
    "A": 1.036411000160938,
    "r2N": 6.218466000965627,
    "max_s": 6.0,
    "delta_t": 0.0,
    "phase": "Deactivated"
  },
  "Nepal": {
    "x": "2016-10-30 00:00:00",
    "y": 1.9963665763311116,
    "yr": "2020-01-01",
    "c": "Nepal",
    "o": 3.0,
    "o2": 0.0,
    "color": "red",
    "x0": 0.7563015952739214,
    "x0_raw": 0.7563015952739214,
    "A": 1.3000187972468653,
    "r2N": 3.9000563917405957,
    "max_s": 3.0,
    "delta_t": 6.427777777777778,
    "phase": "Deceleration"
  },
  "Netherlands": {
    "x": "2014-06-11 00:00:00",
    "y": 2.144686961391835,
    "yr": "2020-01-01",
    "c": "Netherlands",
    "o": 138.0,
    "o2": 0.0,
    "color": "red",
    "x0": 0.5724986435469941,
    "x0_raw": 0.5724986435469941,
    "A": 1.0667343465124135,
    "r2N": 147.20933981871306,
    "max_s": 138.0,
    "delta_t": 11.272222222222222,
    "phase": "Deceleration"
  },
  "New Zealand": {
    "x": "2014-06-26 00:00:00",
    "y": 2.0658433218347962,
    "yr": "2020-01-01",
    "c": "New Zealand",
    "o": 41.0,
    "o2": 0.0,
    "color": "red",
    "x0": 0.5756961239180122,
    "x0_raw": 0.5756961239180122,
    "A": 1.0875946907261334,
    "r2N": 44.59138231977147,
    "max_s": 41.0,
    "delta_t": 11.188888888888888,
    "phase": "Deceleration"
  },
  "Nicaragua": {
    "x": "2020-01-01 00:00:00",
    "y": 8.911073816324619,
    "yr": "2020-01-01",
    "c": "Nicaragua",
    "o": 1.0,
    "o2": 0.0,
    "color": "black",
    "x0": 0.46717213359991683,
    "x0_raw": 0.46717213359991683,
    "A": 1.0000000000000036,
    "r2N": 1.0000000000000036,
    "max_s": 1.0,
    "delta_t": 0.0,
    "phase": "Deactivated"
  },
  "Nigeria": {
    "x": "2016-01-28 00:00:00",
    "y": 2.50197459556345,
    "yr": "2020-01-01",
    "c": "Nigeria",
    "o": 21.0,
    "o2": 0.0,
    "color": "red",
    "x0": 0.6979820588676944,
    "x0_raw": 0.6979820588676944,
    "A": 1.093297912126839,
    "r2N": 22.959256154663617,
    "max_s": 21.0,
    "delta_t": 7.961111111111111,
    "phase": "Deceleration"
  },
  "North Macedonia": {
    "x": "2020-01-01 00:00:00",
    "y": 8.907822629745432,
    "yr": "2020-01-01",
    "c": "North Macedonia",
    "o": 1.0,
    "o2": 0.0,
    "color": "black",
    "x0": 0.30050858062523234,
    "x0_raw": 0.30050858062523234,
    "A": 1.0000000000000038,
    "r2N": 1.0000000000000038,
    "max_s": 1.0,
    "delta_t": 0.0,
    "phase": "Deactivated"
  },
  "Norway": {
    "x": "2014-07-07 00:00:00",
    "y": 1.8473702351989745,
    "yr": "2020-01-01",
    "c": "Norway",
    "o": 84.0,
    "o2": 0.0,
    "color": "red",
    "x0": 0.5780537503019094,
    "x0_raw": 0.5780537503019094,
    "A": 1.1288763801859951,
    "r2N": 94.82561593562359,
    "max_s": 84.0,
    "delta_t": 11.127777777777778,
    "phase": "Deceleration"
  },
  "Pakistan": {
    "x": "2015-09-30 00:00:00",
    "y": 2.489403953370474,
    "yr": "2020-01-01",
    "c": "Pakistan",
    "o": 31.0,
    "o2": 0.0,
    "color": "red",
    "x0": 0.6728390490640225,
    "x0_raw": 0.6728390490640225,
    "A": 1.0714647034128268,
    "r2N": 33.21540580579763,
    "max_s": 31.0,
    "delta_t": 8.627777777777778,
    "phase": "Deceleration"
  },
  "Palestine": {
    "x": "2020-01-01 00:00:00",
    "y": 8.93168145371805,
    "yr": "2020-01-01",
    "c": "Palestine",
    "o": 1.0,
    "o2": 0.0,
    "color": "black",
    "x0": 0.7702055727393057,
    "x0_raw": 0.7702055727393057,
    "A": 1.0000000000000304,
    "r2N": 1.0000000000000304,
    "max_s": 1.0,
    "delta_t": 0.0,
    "phase": "Deactivated"
  },
  "Panama": {
    "x": "2020-01-01 00:00:00",
    "y": 8.905978135896817,
    "yr": "2020-01-01",
    "c": "Panama",
    "o": 1.0,
    "o2": 0.0,
    "color": "black",
    "x0": 0.7803073567284607,
    "x0_raw": 0.7803073567284607,
    "A": 0.9999999999999776,
    "r2N": 0.9999999999999776,
    "max_s": 1.0,
    "delta_t": 0.0,
    "phase": "Deactivated"
  },
  "China": {
    "x": "2014-12-23 00:00:00",
    "y": 2.1963627320258903,
    "yr": "2020-01-01",
    "c": "China",
    "o": 683.0,
    "o2": 0.0,
    "color": "red",
    "x0": 0.613679463036176,
    "x0_raw": 0.613679463036176,
    "A": 1.0858218351483508,
    "r2N": 741.6163134063236,
    "max_s": 683.0,
    "delta_t": 10.188888888888888,
    "phase": "Deceleration"
  },
  "Peru": {
    "x": "2020-01-01 00:00:00",
    "y": 2.648884880972069,
    "yr": "2020-01-01",
    "c": "Peru",
    "o": 10.0,
    "o2": 0.0,
    "color": "black",
    "x0": 0.6601958397008395,
    "x0_raw": 0.6601958397008395,
    "A": 1.0410261514063004,
    "r2N": 10.410261514063004,
    "max_s": 10.0,
    "delta_t": 0.0,
    "phase": "Deactivated"
  },
  "Philippines": {
    "x": "2014-03-11 00:00:00",
    "y": 2.071451154831082,
    "yr": "2020-01-01",
    "c": "Philippines",
    "o": 33.0,
    "o2": 0.0,
    "color": "red",
    "x0": 0.5532223457894475,
    "x0_raw": 0.5532223457894475,
    "A": 1.0736246204400361,
    "r2N": 35.42961247452119,
    "max_s": 33.0,
    "delta_t": 11.783333333333333,
    "phase": "Deceleration"
  },
  "Poland": {
    "x": "2015-03-04 00:00:00",
    "y": 2.2209256083956523,
    "yr": "2020-01-01",
    "c": "Poland",
    "o": 54.0,
    "o2": 0.0,
    "color": "red",
    "x0": 0.6286437154207225,
    "x0_raw": 0.6286437154207225,
    "A": 1.084538306071626,
    "r2N": 58.56506852786781,
    "max_s": 54.0,
    "delta_t": 9.794444444444444,
    "phase": "Deceleration"
  },
  "Portugal": {
    "x": "2014-10-26 00:00:00",
    "y": 2.2975443569138903,
    "yr": "2020-01-01",
    "c": "Portugal",
    "o": 81.0,
    "o2": 0.0,
    "color": "red",
    "x0": 0.6014945772332521,
    "x0_raw": 0.6014945772332521,
    "A": 1.0578388399116696,
    "r2N": 85.68494603284523,
    "max_s": 81.0,
    "delta_t": 10.511111111111111,
    "phase": "Deceleration"
  },
  "Qatar": {
    "x": "2015-10-24 00:00:00",
    "y": 2.5101504864723365,
    "yr": "2020-01-01",
    "c": "Qatar",
    "o": 24.0,
    "o2": 0.0,
    "color": "red",
    "x0": 0.677806234214182,
    "x0_raw": 0.677806234214182,
    "A": 1.0653237857696676,
    "r2N": 25.567770858472024,
    "max_s": 24.0,
    "delta_t": 8.494444444444444,
    "phase": "Deceleration"
  },
  "Romania": {
    "x": "2015-01-25 00:00:00",
    "y": 2.079699870675655,
    "yr": "2020-01-01",
    "c": "Romania",
    "o": 69.0,
    "o2": 0.0,
    "color": "red",
    "x0": 0.6206779485438623,
    "x0_raw": 0.6206779485438623,
    "A": 1.1160217225575595,
    "r2N": 77.0054988564716,
    "max_s": 69.0,
    "delta_t": 10.005555555555556,
    "phase": "Deceleration"
  },
  "Russia": {
    "x": "2014-12-16 00:00:00",
    "y": 2.2543266882261026,
    "yr": "2020-01-01",
    "c": "Russia",
    "o": 9.0,
    "o2": 0.0,
    "color": "red",
    "x0": 0.6120679473413465,
    "x0_raw": 0.6120679473413465,
    "A": 1.0529470345818308,
    "r2N": 9.476523311236477,
    "max_s": 9.0,
    "delta_t": 10.227777777777778,
    "phase": "Deceleration"
  },
  "Saudi Arabia": {
    "x": "2020-01-01 00:00:00",
    "y": 2.6635266553725088,
    "yr": "2020-01-01",
    "c": "Saudi Arabia",
    "o": 21.0,
    "o2": 0.0,
    "color": "black",
    "x0": 0.6581224557319058,
    "x0_raw": 0.6581224557319058,
    "A": 1.0398925432549082,
    "r2N": 21.837743408353074,
    "max_s": 21.0,
    "delta_t": 0.0,
    "phase": "Deactivated"
  },
  "Senegal": {
    "x": "2020-01-01 00:00:00",
    "y": 8.915071419656734,
    "yr": "2020-01-01",
    "c": "Senegal",
    "o": 1.0,
    "o2": 0.0,
    "color": "black",
    "x0": 0.361109230935015,
    "x0_raw": 0.361109230935015,
    "A": 1.0000000000000016,
    "r2N": 1.0000000000000016,
    "max_s": 1.0,
    "delta_t": 0.0,
    "phase": "Deactivated"
  },
  "Serbia": {
    "x": "2015-03-18 00:00:00",
    "y": 2.4145183005361663,
    "yr": "2020-01-01",
    "c": "Serbia",
    "o": 15.0,
    "o2": 0.0,
    "color": "red",
    "x0": 0.6314682759306403,
    "x0_raw": 0.6314682759306403,
    "A": 1.060512097339641,
    "r2N": 15.907681460094613,
    "max_s": 15.0,
    "delta_t": 9.716666666666667,
    "phase": "Deceleration"
  },
  "Singapore": {
    "x": "2020-01-01 00:00:00",
    "y": 2.10575897913395,
    "yr": "2020-01-01",
    "c": "Singapore",
    "o": 68.0,
    "o2": 0.0,
    "color": "black",
    "x0": 0.5296851871773207,
    "x0_raw": 0.5296851871773207,
    "A": 1.0464597790139654,
    "r2N": 71.15926497294964,
    "max_s": 68.0,
    "delta_t": 0.0,
    "phase": "Deactivated"
  },
  "Slovakia": {
    "x": "2020-01-01 00:00:00",
    "y": 2.04804816041746,
    "yr": "2020-01-01",
    "c": "Slovakia",
    "o": 14.0,
    "o2": 0.0,
    "color": "black",
    "x0": 0.5431192482985514,
    "x0_raw": 0.5431192482985514,
    "A": 1.0474498166545056,
    "r2N": 14.664297433163078,
    "max_s": 14.0,
    "delta_t": 0.0,
    "phase": "Deactivated"
  },
  "Slovenia": {
    "x": "2020-01-01 00:00:00",
    "y": 2.164824762604014,
    "yr": "2020-01-01",
    "c": "Slovenia",
    "o": 26.0,
    "o2": 0.0,
    "color": "black",
    "x0": 0.48638732333062223,
    "x0_raw": 0.48638732333062223,
    "A": 1.0336811250386886,
    "r2N": 26.875709251005905,
    "max_s": 26.0,
    "delta_t": 0.0,
    "phase": "Deactivated"
  },
  "South Africa": {
    "x": "2014-12-21 00:00:00",
    "y": 2.0518172533447556,
    "yr": "2020-01-01",
    "c": "South Africa",
    "o": 79.0,
    "o2": 0.0,
    "color": "red",
    "x0": 0.6132036086764051,
    "x0_raw": 0.6132036086764051,
    "A": 1.1189581174766523,
    "r2N": 88.39769128065554,
    "max_s": 79.0,
    "delta_t": 10.2,
    "phase": "Deceleration"
  },
  "South Korea": {
    "x": "2020-01-01 00:00:00",
    "y": 2.5082361346055455,
    "yr": "2020-01-01",
    "c": "South Korea",
    "o": 53.0,
    "o2": 0.0,
    "color": "black",
    "x0": 0.6204380796233275,
    "x0_raw": 0.6204380796233275,
    "A": 1.0422037816000829,
    "r2N": 55.23680042480439,
    "max_s": 53.0,
    "delta_t": 0.0,
    "phase": "Deactivated"
  },
  "Spain": {
    "x": "2015-01-09 00:00:00",
    "y": 2.2383006351549755,
    "yr": "2020-01-01",
    "c": "Spain",
    "o": 329.0,
    "o2": 0.0,
    "color": "red",
    "x0": 0.6172308206939033,
    "x0_raw": 0.6172308206939033,
    "A": 1.0787651645203755,
    "r2N": 354.91373912720354,
    "max_s": 329.0,
    "delta_t": 10.094444444444445,
    "phase": "Deceleration"
  },
  "Sri Lanka": {
    "x": "2016-01-04 00:00:00",
    "y": 2.2035851075061115,
    "yr": "2020-01-01",
    "c": "Sri Lanka",
    "o": 17.0,
    "o2": 0.0,
    "color": "red",
    "x0": 0.6930373641157839,
    "x0_raw": 0.6930373641157839,
    "A": 1.1411867849815178,
    "r2N": 19.400175344685803,
    "max_s": 17.0,
    "delta_t": 8.094444444444445,
    "phase": "Deceleration"
  },
  "Sweden": {
    "x": "2014-09-08 00:00:00",
    "y": 2.299964308438012,
    "yr": "2020-01-01",
    "c": "Sweden",
    "o": 119.0,
    "o2": 0.0,
    "color": "red",
    "x0": 0.5912981133851085,
    "x0_raw": 0.5912981133851085,
    "A": 1.0521683202539533,
    "r2N": 125.20803011022045,
    "max_s": 119.0,
    "delta_t": 10.777777777777779,
    "phase": "Deceleration"
  },
  "Switzerland": {
    "x": "2014-09-18 00:00:00",
    "y": 2.076006890953811,
    "yr": "2020-01-01",
    "c": "Switzerland",
    "o": 65.0,
    "o2": 0.0,
    "color": "red",
    "x0": 0.5933773703317243,
    "x0_raw": 0.5933773703317243,
    "A": 1.0998076874748461,
    "r2N": 71.487499685865,
    "max_s": 65.0,
    "delta_t": 10.722222222222221,
    "phase": "Deceleration"
  },
  "Taiwan": {
    "x": "2014-06-09 00:00:00",
    "y": 2.148207536849631,
    "yr": "2020-01-01",
    "c": "Taiwan",
    "o": 97.0,
    "o2": 0.0,
    "color": "red",
    "x0": 0.572040725563359,
    "x0_raw": 0.572040725563359,
    "A": 1.061090861970865,
    "r2N": 102.92581361117391,
    "max_s": 97.0,
    "delta_t": 11.283333333333333,
    "phase": "Deceleration"
  },
  "Tanzania": {
    "x": "2020-01-01 00:00:00",
    "y": 3.2013943631286255,
    "yr": "2020-01-01",
    "c": "Tanzania",
    "o": 2.0,
    "o2": 0.0,
    "color": "black",
    "x0": 0.5442278092016252,
    "x0_raw": 0.5442278092016252,
    "A": 1.0103396251813133,
    "r2N": 2.0206792503626265,
    "max_s": 2.0,
    "delta_t": 0.0,
    "phase": "Deactivated"
  },
  "Thailand": {
    "x": "2020-01-01 00:00:00",
    "y": 2.5211409784340373,
    "yr": "2020-01-01",
    "c": "Thailand",
    "o": 42.0,
    "o2": 0.0,
    "color": "black",
    "x0": 0.573263742935284,
    "x0_raw": 0.573263742935284,
    "A": 1.0270396460009554,
    "r2N": 43.13566513204013,
    "max_s": 42.0,
    "delta_t": 0.0,
    "phase": "Deactivated"
  },
  "Togo": {
    "x": "2020-01-01 00:00:00",
    "y": 8.932983152049424,
    "yr": "2020-01-01",
    "c": "Togo",
    "o": 1.0,
    "o2": 0.0,
    "color": "black",
    "x0": 0.603533880903608,
    "x0_raw": 0.603533880903608,
    "A": 0.9999999999999899,
    "r2N": 0.9999999999999899,
    "max_s": 1.0,
    "delta_t": 0.0,
    "phase": "Deactivated"
  },
  "Trinidad Tobago": {
    "x": "2020-01-01 00:00:00",
    "y": 2.6919468961982522,
    "yr": "2020-01-01",
    "c": "Trinidad Tobago",
    "o": 2.0,
    "o2": 0.0,
    "color": "black",
    "x0": 0.5168691778486826,
    "x0_raw": 0.5168691778486826,
    "A": 1.0206064507426649,
    "r2N": 2.0412129014853297,
    "max_s": 2.0,
    "delta_t": 0.0,
    "phase": "Deactivated"
  },
  "Tunisia": {
    "x": "2020-01-01 00:00:00",
    "y": 8.91608707187031,
    "yr": "2020-01-01",
    "c": "Tunisia",
    "o": 1.0,
    "o2": 0.0,
    "color": "black",
    "x0": 0.6287884850191988,
    "x0_raw": 0.6287884850191988,
    "A": 0.9999999999999891,
    "r2N": 0.9999999999999891,
    "max_s": 1.0,
    "delta_t": 0.0,
    "phase": "Deactivated"
  },
  "Turkey": {
    "x": "2020-01-01 00:00:00",
    "y": 2.714431123248422,
    "yr": "2020-01-01",
    "c": "Turkey",
    "o": 59.0,
    "o2": 0.0,
    "color": "black",
    "x0": 0.6770022885775716,
    "x0_raw": 0.6770022885775716,
    "A": 1.04054604635974,
    "r2N": 61.392216735224665,
    "max_s": 59.0,
    "delta_t": 0.0,
    "phase": "Deactivated"
  },
  "U Arab Emirates": {
    "x": "2015-04-24 00:00:00",
    "y": 1.8641165321098672,
    "yr": "2020-01-01",
    "c": "U Arab Emirates",
    "o": 31.0,
    "o2": 0.0,
    "color": "red",
    "x0": 0.6392970413232181,
    "x0_raw": 0.6392970413232181,
    "A": 1.191329971389394,
    "r2N": 36.93122911307121,
    "max_s": 31.0,
    "delta_t": 9.511111111111111,
    "phase": "Deceleration"
  },
  "Uganda": {
    "x": "2020-01-01 00:00:00",
    "y": 8.921401541167938,
    "yr": "2020-01-01",
    "c": "Uganda",
    "o": 1.0,
    "o2": 0.0,
    "color": "black",
    "x0": 0.37121271312763554,
    "x0_raw": 0.37121271312763554,
    "A": 0.9999999999999627,
    "r2N": 0.9999999999999627,
    "max_s": 1.0,
    "delta_t": 0.0,
    "phase": "Deactivated"
  },
  "Ukraine": {
    "x": "2020-01-01 00:00:00",
    "y": 4.919676223443295,
    "yr": "2020-01-01",
    "c": "Ukraine",
    "o": 2.0,
    "o2": 0.0,
    "color": "black",
    "x0": 0.7753225921898068,
    "x0_raw": 0.7753225921898068,
    "A": 1.0030731766676446,
    "r2N": 2.0061463533352892,
    "max_s": 2.0,
    "delta_t": 0.0,
    "phase": "Deactivated"
  },
  "Uruguay": {
    "x": "2020-01-01 00:00:00",
    "y": 3.5284638226299077,
    "yr": "2020-01-01",
    "c": "Uruguay",
    "o": 2.0,
    "o2": 0.0,
    "color": "black",
    "x0": 0.4322871206115539,
    "x0_raw": 0.4322871206115539,
    "A": 1.005142347188027,
    "r2N": 2.010284694376054,
    "max_s": 2.0,
    "delta_t": 0.0,
    "phase": "Deactivated"
  },
  "Venezuela": {
    "x": "2020-01-01 00:00:00",
    "y": 8.908749001691614,
    "yr": "2020-01-01",
    "c": "Venezuela",
    "o": 1.0,
    "o2": 0.0,
    "color": "black",
    "x0": 0.42171746120369163,
    "x0_raw": 0.42171746120369163,
    "A": 0.9999999999999737,
    "r2N": 0.9999999999999737,
    "max_s": 1.0,
    "delta_t": 0.0,
    "phase": "Deactivated"
  },
  "Vietnam": {
    "x": "2020-01-01 00:00:00",
    "y": 2.980447593996326,
    "yr": "2020-01-01",
    "c": "Vietnam",
    "o": 5.0,
    "o2": 0.0,
    "color": "black",
    "x0": 0.6399233618388945,
    "x0_raw": 0.6399233618388945,
    "A": 1.0306028247342576,
    "r2N": 5.153014123671288,
    "max_s": 5.0,
    "delta_t": 0.0,
    "phase": "Deactivated"
  },
  "Zimbabwe": {
    "x": "2014-09-22 00:00:00",
    "y": 1.9448199656353322,
    "yr": "2020-01-01",
    "c": "Zimbabwe",
    "o": 2.0,
    "o2": 0.0,
    "color": "red",
    "x0": 0.594163205634964,
    "x0_raw": 0.594163205634964,
    "A": 1.1112664082097943,
    "r2N": 2.2225328164195886,
    "max_s": 2.0,
    "delta_t": 10.7,
    "phase": "Deceleration"
  },
  "USA": {
    "x": "2013-08-18 00:00:00",
    "y": 1.9977646848702972,
    "yr": "2020-01-01",
    "c": "USA",
    "o": 1047.0,
    "o2": 0.0,
    "color": "red",
    "x0": 0.5099751048162355,
    "x0_raw": 0.5099751048162355,
    "A": 1.0571433814271796,
    "r2N": 1106.829120354257,
    "max_s": 1047.0,
    "delta_t": 12.922222222222222,
    "phase": "Deceleration"
  },
  "UK": {
    "x": "2013-10-03 00:00:00",
    "y": 1.8903264375415307,
    "yr": "2020-01-01",
    "c": "UK",
    "o": 564.0,
    "o2": 0.0,
    "color": "red",
    "x0": 0.5196838471100574,
    "x0_raw": 0.5196838471100574,
    "A": 1.084103762085592,
    "r2N": 611.4345218162739,
    "max_s": 564.0,
    "delta_t": 12.666666666666666,
    "phase": "Deceleration"
  }
}