{
  "Albania": {
    "x": "2021-07-01 00:00:00",
    "y": 2.7404370730817407,
    "yr": "2021-07-01",
    "c": "Albania",
    "o": 3.0,
    "o2": 0.0,
    "color": "black",
    "x0": 0.6295479189465982,
    "x0_raw": 0.6295479189465982,
    "A": 1.0314969251294144,
    "r2N": 3.094490775388243,
    "max_s": 3.0,
    "delta_t": 0.0,
    "phase": "Deactivated"
  },
  "Algeria": {
    "x": "2021-07-01 00:00:00",
    "y": 2.9486081381661413,
    "yr": "2021-07-01",
    "c": "Algeria",
    "o": 5.0,
    "o2": 0.0,
    "color": "black",
    "x0": 0.5745636493404025,
    "x0_raw": 0.5745636493404025,
    "A": 1.0116020486003745,
    "r2N": 5.058010243001872,
    "max_s": 5.0,
    "delta_t": 0.0,
    "phase": "Deactivated"
  },
  "Angola": {
    "x": "2021-07-01 00:00:00",
    "y": 8.900027188169458,
    "yr": "2021-07-01",
    "c": "Angola",
    "o": 1.0,
    "o2": 0.0,
    "color": "black",
    "x0": 0.7500046014204333,
    "x0_raw": 0.7500046014204333,
    "A": 1.000000000000008,
    "r2N": 1.000000000000008,
    "max_s": 1.0,
    "delta_t": 0.0,
    "phase": "Deactivated"
  },
  "Argentina": {
    "x": "2017-01-19 00:00:00",
    "y": 2.689163092273297,
    "yr": "2021-07-01",
    "c": "Argentina",
    "o": 14.0,
    "o2": 0.0,
    "color": "red",
    "x0": 0.693464688736792,
    "x0_raw": 0.693464688736792,
    "A": 1.060156349761379,
    "r2N": 14.842188896659307,
    "max_s": 14.0,
    "delta_t": 9.016666666666667,
    "phase": "Deceleration"
  },
  "Australia": {
    "x": "2015-07-14 00:00:00",
    "y": 1.9042330312463982,
    "yr": "2021-07-01",
    "c": "Australia",
    "o": 398.0,
    "o2": 0.0,
    "color": "red",
    "x0": 0.5885012933470394,
    "x0_raw": 0.5885012933470394,
    "A": 1.1104589472490989,
    "r2N": 441.96266100514134,
    "max_s": 398.0,
    "delta_t": 12.1,
    "phase": "Deceleration"
  },
  "Austria": {
    "x": "2016-09-07 00:00:00",
    "y": 1.8958578585256234,
    "yr": "2021-07-01",
    "c": "Austria",
    "o": 68.0,
    "o2": 0.0,
    "color": "red",
    "x0": 0.6681358052366363,
    "x0_raw": 0.6681358052366363,
    "A": 1.1884533543761573,
    "r2N": 80.8148280975787,
    "max_s": 68.0,
    "delta_t": 9.761111111111111,
    "phase": "Deceleration"
  },
  "Bahrain": {
    "x": "2021-07-01 00:00:00",
    "y": 4.918978152069519,
    "yr": "2021-07-01",
    "c": "Bahrain",
    "o": 2.0,
    "o2": 0.0,
    "color": "black",
    "x0": 0.8005851033797438,
    "x0_raw": 0.8005851033797438,
    "A": 1.0035107647289832,
    "r2N": 2.0070215294579663,
    "max_s": 2.0,
    "delta_t": 0.0,
    "phase": "Deactivated"
  },
  "Bangladesh": {
    "x": "2017-07-19 00:00:00",
    "y": 2.110977651213444,
    "yr": "2021-07-01",
    "c": "Bangladesh",
    "o": 11.0,
    "o2": 0.0,
    "color": "red",
    "x0": 0.7275542906840563,
    "x0_raw": 0.7275542906840563,
    "A": 1.1956734480444153,
    "r2N": 13.152407928488568,
    "max_s": 11.0,
    "delta_t": 8.011111111111111,
    "phase": "Deceleration"
  },
  "Belgium": {
    "x": "2015-11-23 00:00:00",
    "y": 1.8989310660159298,
    "yr": "2021-07-01",
    "c": "Belgium",
    "o": 97.0,
    "o2": 0.0,
    "color": "red",
    "x0": 0.6134738420689527,
    "x0_raw": 0.6134738420689527,
    "A": 1.119296282065574,
    "r2N": 108.57173936036068,
    "max_s": 97.0,
    "delta_t": 11.366666666666667,
    "phase": "Deceleration"
  },
  "Bhutan": {
    "x": "2021-07-01 00:00:00",
    "y": 8.920872274734693,
    "yr": "2021-07-01",
    "c": "Bhutan",
    "o": 1.0,
    "o2": 0.0,
    "color": "black",
    "x0": 0.7398981717762941,
    "x0_raw": 0.7398981717762941,
    "A": 0.9999999999999701,
    "r2N": 0.9999999999999701,
    "max_s": 1.0,
    "delta_t": 0.0,
    "phase": "Deactivated"
  },
  "Brazil": {
    "x": "2017-02-24 00:00:00",
    "y": 2.3715573632443983,
    "yr": "2021-07-01",
    "c": "Brazil",
    "o": 156.0,
    "o2": 0.0,
    "color": "red",
    "x0": 0.7002116154681307,
    "x0_raw": 0.7002116154681307,
    "A": 1.1036223771453129,
    "r2N": 172.1650908346688,
    "max_s": 156.0,
    "delta_t": 8.816666666666666,
    "phase": "Deceleration"
  },
  "Bulgaria": {
    "x": "2017-05-07 00:00:00",
    "y": 2.322622344020143,
    "yr": "2021-07-01",
    "c": "Bulgaria",
    "o": 2.0,
    "o2": 0.0,
    "color": "red",
    "x0": 0.7138032984372119,
    "x0_raw": 0.7138032984372119,
    "A": 1.1048401537053096,
    "r2N": 2.2096803074106193,
    "max_s": 2.0,
    "delta_t": 8.416666666666666,
    "phase": "Deceleration"
  },
  "Burkina Faso": {
    "x": "2021-07-01 00:00:00",
    "y": 8.908671740400845,
    "yr": "2021-07-01",
    "c": "Burkina Faso",
    "o": 1.0,
    "o2": 0.0,
    "color": "black",
    "x0": 0.7247418974430672,
    "x0_raw": 0.7247418974430672,
    "A": 1.0000000000000262,
    "r2N": 1.0000000000000262,
    "max_s": 1.0,
    "delta_t": 0.0,
    "phase": "Deactivated"
  },
  "Cameroon": {
    "x": "2021-07-01 00:00:00",
    "y": 8.921742209609397,
    "yr": "2021-07-01",
    "c": "Cameroon",
    "o": 1.0,
    "o2": 0.0,
    "color": "black",
    "x0": 0.7348499359277757,
    "x0_raw": 0.7348499359277757,
    "A": 1.000000000000009,
    "r2N": 1.000000000000009,
    "max_s": 1.0,
    "delta_t": 0.0,
    "phase": "Deactivated"
  },
  "Canada": {
    "x": "2016-06-03 00:00:00",
    "y": 1.8909888643969386,
    "yr": "2021-07-01",
    "c": "Canada",
    "o": 329.0,
    "o2": 0.0,
    "color": "red",
    "x0": 0.6499622045292371,
    "x0_raw": 0.6499622045292371,
    "A": 1.1676042616584534,
    "r2N": 384.1418020856312,
    "max_s": 329.0,
    "delta_t": 10.294444444444444,
    "phase": "Deceleration"
  },
  "Chile": {
    "x": "2016-07-19 00:00:00",
    "y": 1.988102175481792,
    "yr": "2021-07-01",
    "c": "Chile",
    "o": 45.0,
    "o2": 0.0,
    "color": "red",
    "x0": 0.6586672476872452,
    "x0_raw": 0.6586672476872452,
    "A": 1.1377492431804859,
    "r2N": 51.19871594312186,
    "max_s": 45.0,
    "delta_t": 10.03888888888889,
    "phase": "Deceleration"
  },
  "Colombia": {
    "x": "2017-03-22 00:00:00",
    "y": 2.0918194852044985,
    "yr": "2021-07-01",
    "c": "Colombia",
    "o": 60.0,
    "o2": 0.0,
    "color": "red",
    "x0": 0.705037228635221,
    "x0_raw": 0.705037228635221,
    "A": 1.1707363114060068,
    "r2N": 70.2441786843604,
    "max_s": 60.0,
    "delta_t": 8.672222222222222,
    "phase": "Deceleration"
  },
  "Costa Rica": {
    "x": "2021-07-01 00:00:00",
    "y": 3.2672372207051064,
    "yr": "2021-07-01",
    "c": "Costa Rica",
    "o": 5.0,
    "o2": 0.0,
    "color": "black",
    "x0": 0.7366831992813354,
    "x0_raw": 0.7366831992813354,
    "A": 1.03024792917697,
    "r2N": 5.15123964588485,
    "max_s": 5.0,
    "delta_t": 0.0,
    "phase": "Deactivated"
  },
  "Croatia": {
    "x": "2017-11-22 00:00:00",
    "y": 2.2347124084967884,
    "yr": "2021-07-01",
    "c": "Croatia",
    "o": 14.0,
    "o2": 0.0,
    "color": "red",
    "x0": 0.7514288426701724,
    "x0_raw": 0.7514288426701724,
    "A": 1.2116857986410339,
    "r2N": 16.963601180974475,
    "max_s": 14.0,
    "delta_t": 7.311111111111111,
    "phase": "Deceleration"
  },
  "Cuba": {
    "x": "2021-07-01 00:00:00",
    "y": 8.909025645148255,
    "yr": "2021-07-01",
    "c": "Cuba",
    "o": 1.0,
    "o2": 0.0,
    "color": "black",
    "x0": 0.8055567349755764,
    "x0_raw": 0.8055567349755764,
    "A": 1.0000000000000078,
    "r2N": 1.0000000000000078,
    "max_s": 1.0,
    "delta_t": 0.0,
    "phase": "Deactivated"
  },
  "Cyprus": {
    "x": "2016-12-15 00:00:00",
    "y": 2.4808808071551685,
    "yr": "2021-07-01",
    "c": "Cyprus",
    "o": 9.0,
    "o2": 0.0,
    "color": "red",
    "x0": 0.6868282627664318,
    "x0_raw": 0.6868282627664318,
    "A": 1.069496263450443,
    "r2N": 9.625466371053987,
    "max_s": 9.0,
    "delta_t": 9.21111111111111,
    "phase": "Deceleration"
  },
  "Czech Republic": {
    "x": "2017-03-31 00:00:00",
    "y": 2.0876934504663205,
    "yr": "2021-07-01",
    "c": "Czech Republic",
    "o": 50.0,
    "o2": 0.0,
    "color": "red",
    "x0": 0.706854572101534,
    "x0_raw": 0.706854572101534,
    "A": 1.196318608573986,
    "r2N": 59.8159304286993,
    "max_s": 50.0,
    "delta_t": 8.622222222222222,
    "phase": "Deceleration"
  },
  "Denmark": {
    "x": "2016-01-20 00:00:00",
    "y": 1.9726579037288348,
    "yr": "2021-07-01",
    "c": "Denmark",
    "o": 102.0,
    "o2": 0.0,
    "color": "red",
    "x0": 0.6245451630229393,
    "x0_raw": 0.6245451630229393,
    "A": 1.1323188427550108,
    "r2N": 115.4965219610111,
    "max_s": 102.0,
    "delta_t": 11.044444444444444,
    "phase": "Deceleration"
  },
  "Ecuador": {
    "x": "2017-10-19 00:00:00",
    "y": 2.7091814774193885,
    "yr": "2021-07-01",
    "c": "Ecuador",
    "o": 12.0,
    "o2": 0.0,
    "color": "red",
    "x0": 0.7449260907834302,
    "x0_raw": 0.7449260907834302,
    "A": 1.075695308118252,
    "r2N": 12.908343697419024,
    "max_s": 12.0,
    "delta_t": 7.5,
    "phase": "Deceleration"
  },
  "Egypt": {
    "x": "2021-07-01 00:00:00",
    "y": 3.159350462003234,
    "yr": "2021-07-01",
    "c": "Egypt",
    "o": 11.0,
    "o2": 0.0,
    "color": "black",
    "x0": 0.7571052881614988,
    "x0_raw": 0.7571052881614988,
    "A": 1.0401258094253836,
    "r2N": 11.441383903679219,
    "max_s": 11.0,
    "delta_t": 0.0,
    "phase": "Deactivated"
  },
  "Estonia": {
    "x": "2016-06-28 00:00:00",
    "y": 2.26811340432054,
    "yr": "2021-07-01",
    "c": "Estonia",
    "o": 10.0,
    "o2": 0.0,
    "color": "red",
    "x0": 0.6547275851873222,
    "x0_raw": 0.6547275851873222,
    "A": 1.090895838830825,
    "r2N": 10.90895838830825,
    "max_s": 10.0,
    "delta_t": 10.155555555555555,
    "phase": "Deceleration"
  },
  "Eswatini": {
    "x": "2021-07-01 00:00:00",
    "y": 8.909500364185487,
    "yr": "2021-07-01",
    "c": "Eswatini",
    "o": 1.0,
    "o2": 0.0,
    "color": "black",
    "x0": 0.8005072941748057,
    "x0_raw": 0.8005072941748057,
    "A": 1.0000000000000124,
    "r2N": 1.0000000000000124,
    "max_s": 1.0,
    "delta_t": 0.0,
    "phase": "Deactivated"
  },
  "Ethiopia": {
    "x": "2018-09-02 00:00:00",
    "y": 3.0357932658984867,
    "yr": "2021-07-01",
    "c": "Ethiopia",
    "o": 3.0,
    "o2": 0.0,
    "color": "red",
    "x0": 0.8050176827970539,
    "x0_raw": 0.8050176827970539,
    "A": 1.0842372527422683,
    "r2N": 3.252711758226805,
    "max_s": 3.0,
    "delta_t": 5.733333333333333,
    "phase": "Deceleration"
  },
  "Fiji": {
    "x": "2015-11-05 00:00:00",
    "y": 1.57922969088082,
    "yr": "2021-07-01",
    "c": "Fiji",
    "o": 4.0,
    "o2": 0.0,
    "color": "red",
    "x0": 0.6101710065349009,
    "x0_raw": 0.6101710065349009,
    "A": 1.2532324615317394,
    "r2N": 5.012929846126958,
    "max_s": 4.0,
    "delta_t": 11.466666666666667,
    "phase": "Deceleration"
  },
  "Finland": {
    "x": "2016-07-04 00:00:00",
    "y": 1.756802783219956,
    "yr": "2021-07-01",
    "c": "Finland",
    "o": 115.0,
    "o2": 0.0,
    "color": "red",
    "x0": 0.6558073884610213,
    "x0_raw": 0.6558073884610213,
    "A": 1.2200454296077907,
    "r2N": 140.30522440489594,
    "max_s": 115.0,
    "delta_t": 10.122222222222222,
    "phase": "Deceleration"
  },
  "France": {
    "x": "2017-02-01 00:00:00",
    "y": 1.9299505687526937,
    "yr": "2021-07-01",
    "c": "France",
    "o": 178.0,
    "o2": 0.0,
    "color": "red",
    "x0": 0.6957935214627673,
    "x0_raw": 0.6957935214627673,
    "A": 1.2063725748890308,
    "r2N": 214.73431833024748,
    "max_s": 178.0,
    "delta_t": 8.944444444444445,
    "phase": "Deceleration"
  },
  "Germany": {
    "x": "2016-04-02 00:00:00",
    "y": 1.875282423586501,
    "yr": "2021-07-01",
    "c": "Germany",
    "o": 372.0,
    "o2": 0.0,
    "color": "red",
    "x0": 0.6381979639713036,
    "x0_raw": 0.6381979639713036,
    "A": 1.152694902087445,
    "r2N": 428.80250357652955,
    "max_s": 372.0,
    "delta_t": 10.63888888888889,
    "phase": "Deceleration"
  },
  "Ghana": {
    "x": "2015-12-21 00:00:00",
    "y": 1.9144894357448756,
    "yr": "2021-07-01",
    "c": "Ghana",
    "o": 2.0,
    "o2": 0.0,
    "color": "red",
    "x0": 0.618805768256835,
    "x0_raw": 0.618805768256835,
    "A": 1.1298076516676496,
    "r2N": 2.2596153033352993,
    "max_s": 2.0,
    "delta_t": 11.21111111111111,
    "phase": "Deceleration"
  },
  "Greece": {
    "x": "2016-02-03 00:00:00",
    "y": 2.0301915444173684,
    "yr": "2021-07-01",
    "c": "Greece",
    "o": 85.0,
    "o2": 0.0,
    "color": "red",
    "x0": 0.6271239722335249,
    "x0_raw": 0.6271239722335249,
    "A": 1.103592944415377,
    "r2N": 93.80540027530704,
    "max_s": 85.0,
    "delta_t": 10.966666666666667,
    "phase": "Deceleration"
  },
  "Hungary": {
    "x": "2021-07-01 00:00:00",
    "y": 1.8627682777415302,
    "yr": "2021-07-01",
    "c": "Hungary",
    "o": 36.0,
    "o2": 0.0,
    "color": "black",
    "x0": 0.37155387705587434,
    "x0_raw": 0.37155387705587434,
    "A": 1.005489919244778,
    "r2N": 36.197637092812,
    "max_s": 36.0,
    "delta_t": 0.0,
    "phase": "Deactivated"
  },
  "Iceland": {
    "x": "2021-07-01 00:00:00",
    "y": 3.0864174399526,
    "yr": "2021-07-01",
    "c": "Iceland",
    "o": 11.0,
    "o2": 0.0,
    "color": "black",
    "x0": 0.7278215878000444,
    "x0_raw": 0.7278215878000444,
    "A": 1.040023485921195,
    "r2N": 11.440258345133145,
    "max_s": 11.0,
    "delta_t": 0.0,
    "phase": "Deactivated"
  },
  "India": {
    "x": "2016-12-16 00:00:00",
    "y": 2.068907186738795,
    "yr": "2021-07-01",
    "c": "India",
    "o": 451.0,
    "o2": 0.0,
    "color": "red",
    "x0": 0.6870563792404246,
    "x0_raw": 0.6870563792404246,
    "A": 1.1597604420284016,
    "r2N": 523.0519593548091,
    "max_s": 451.0,
    "delta_t": 9.205555555555556,
    "phase": "Deceleration"
  },
  "Indonesia": {
    "x": "2016-06-05 00:00:00",
    "y": 2.5508200266505123,
    "yr": "2021-07-01",
    "c": "Indonesia",
    "o": 27.0,
    "o2": 0.0,
    "color": "red",
    "x0": 0.6502784132223117,
    "x0_raw": 0.6502784132223117,
    "A": 1.0521804755570519,
    "r2N": 28.4088728400404,
    "max_s": 27.0,
    "delta_t": 10.283333333333333,
    "phase": "Deceleration"
  },
  "Iran": {
    "x": "2017-03-21 00:00:00",
    "y": 2.5775299052390634,
    "yr": "2021-07-01",
    "c": "Iran",
    "o": 60.0,
    "o2": 0.0,
    "color": "red",
    "x0": 0.7049797686700087,
    "x0_raw": 0.7049797686700087,
    "A": 1.0629267328472232,
    "r2N": 63.77560397083339,
    "max_s": 60.0,
    "delta_t": 8.677777777777777,
    "phase": "Deceleration"
  },
  "Iraq": {
    "x": "2021-07-01 00:00:00",
    "y": 3.1777109729538924,
    "yr": "2021-07-01",
    "c": "Iraq",
    "o": 4.0,
    "o2": 0.0,
    "color": "black",
    "x0": 0.74263832525514,
    "x0_raw": 0.74263832525514,
    "A": 1.0343921526659197,
    "r2N": 4.137568610663679,
    "max_s": 4.0,
    "delta_t": 0.0,
    "phase": "Deactivated"
  },
  "Ireland": {
    "x": "2016-05-12 00:00:00",
    "y": 1.9144751798032031,
    "yr": "2021-07-01",
    "c": "Ireland",
    "o": 72.0,
    "o2": 0.0,
    "color": "red",
    "x0": 0.6458076827356882,
    "x0_raw": 0.6458076827356882,
    "A": 1.1605182330038888,
    "r2N": 83.55731277627999,
    "max_s": 72.0,
    "delta_t": 10.416666666666666,
    "phase": "Deceleration"
  },
  "Israel": {
    "x": "2016-02-12 00:00:00",
    "y": 2.2426215148310966,
    "yr": "2021-07-01",
    "c": "Israel",
    "o": 9.0,
    "o2": 0.0,
    "color": "red",
    "x0": 0.6288611555439727,
    "x0_raw": 0.6288611555439727,
    "A": 1.0590477494410704,
    "r2N": 9.531429744969634,
    "max_s": 9.0,
    "delta_t": 10.916666666666666,
    "phase": "Deceleration"
  },
  "Italy": {
    "x": "2016-08-18 00:00:00",
    "y": 2.157610377537743,
    "yr": "2021-07-01",
    "c": "Italy",
    "o": 486.0,
    "o2": 0.0,
    "color": "red",
    "x0": 0.6643869327122884,
    "x0_raw": 0.6643869327122884,
    "A": 1.1106061385138999,
    "r2N": 539.7545833177553,
    "max_s": 486.0,
    "delta_t": 9.872222222222222,
    "phase": "Deceleration"
  },
  "Japan": {
    "x": "2017-05-30 00:00:00",
    "y": 1.7818173103751886,
    "yr": "2021-07-01",
    "c": "Japan",
    "o": 87.0,
    "o2": 0.0,
    "color": "red",
    "x0": 0.7182231583007846,
    "x0_raw": 0.7182231583007846,
    "A": 1.2946950992049444,
    "r2N": 112.63847363083016,
    "max_s": 87.0,
    "delta_t": 8.28888888888889,
    "phase": "Deceleration"
  },
  "Jordan": {
    "x": "2021-07-01 00:00:00",
    "y": 3.0372271009308687,
    "yr": "2021-07-01",
    "c": "Jordan",
    "o": 5.0,
    "o2": 0.0,
    "color": "black",
    "x0": 0.7098451368893692,
    "x0_raw": 0.7098451368893692,
    "A": 1.0130441089985622,
    "r2N": 5.065220544992811,
    "max_s": 5.0,
    "delta_t": 0.0,
    "phase": "Deactivated"
  },
  "Kazakhstan": {
    "x": "2021-07-01 00:00:00",
    "y": 8.910324505888596,
    "yr": "2021-07-01",
    "c": "Kazakhstan",
    "o": 1.0,
    "o2": 0.0,
    "color": "black",
    "x0": 0.7954530111629663,
    "x0_raw": 0.7954530111629663,
    "A": 0.9999999999999929,
    "r2N": 0.9999999999999929,
    "max_s": 1.0,
    "delta_t": 0.0,
    "phase": "Deactivated"
  },
  "Kenya": {
    "x": "2021-07-01 00:00:00",
    "y": 3.3755948883484366,
    "yr": "2021-07-01",
    "c": "Kenya",
    "o": 4.0,
    "o2": 0.0,
    "color": "black",
    "x0": 0.6168731260599234,
    "x0_raw": 0.6168731260599234,
    "A": 0.9917866828838857,
    "r2N": 3.967146731535543,
    "max_s": 4.0,
    "delta_t": 0.0,
    "phase": "Deactivated"
  },
  "Kuwait": {
    "x": "2021-07-01 00:00:00",
    "y": 2.5673152347500543,
    "yr": "2021-07-01",
    "c": "Kuwait",
    "o": 6.0,
    "o2": 0.0,
    "color": "black",
    "x0": 0.6119323835620706,
    "x0_raw": 0.6119323835620706,
    "A": 0.990989274300059,
    "r2N": 5.945935645800354,
    "max_s": 6.0,
    "delta_t": 0.0,
    "phase": "Deactivated"
  },
  "Latvia": {
    "x": "2017-12-13 00:00:00",
    "y": 1.8301208780452494,
    "yr": "2021-07-01",
    "c": "Latvia",
    "o": 8.0,
    "o2": 0.0,
    "color": "red",
    "x0": 0.7553413588801349,
    "x0_raw": 0.7553413588801349,
    "A": 1.345827067935596,
    "r2N": 10.766616543484767,
    "max_s": 8.0,
    "delta_t": 7.194444444444445,
    "phase": "Deceleration"
  },
  "Lebanon": {
    "x": "2016-10-27 00:00:00",
    "y": 2.2328434240531134,
    "yr": "2021-07-01",
    "c": "Lebanon",
    "o": 14.0,
    "o2": 0.0,
    "color": "red",
    "x0": 0.6776193026901808,
    "x0_raw": 0.6776193026901808,
    "A": 1.1246300989771043,
    "r2N": 15.74482138567946,
    "max_s": 14.0,
    "delta_t": 9.483333333333333,
    "phase": "Deceleration"
  },
  "Lithuania": {
    "x": "2021-07-01 00:00:00",
    "y": 3.239778872590433,
    "yr": "2021-07-01",
    "c": "Lithuania",
    "o": 16.0,
    "o2": 0.0,
    "color": "black",
    "x0": 0.7576470991848868,
    "x0_raw": 0.7576470991848868,
    "A": 1.0417004665471448,
    "r2N": 16.667207464754316,
    "max_s": 16.0,
    "delta_t": 0.0,
    "phase": "Deactivated"
  },
  "Luxembourg": {
    "x": "2021-07-01 00:00:00",
    "y": 2.5038609774793477,
    "yr": "2021-07-01",
    "c": "Luxembourg",
    "o": 10.0,
    "o2": 0.0,
    "color": "black",
    "x0": 0.4359213811639689,
    "x0_raw": 0.4359213811639689,
    "A": 0.9938083971316014,
    "r2N": 9.938083971316015,
    "max_s": 10.0,
    "delta_t": 0.0,
    "phase": "Deactivated"
  },
  "Madagascar": {
    "x": "2017-07-29 00:00:00",
    "y": 2.2127683585599227,
    "yr": "2021-07-01",
    "c": "Madagascar",
    "o": 2.0,
    "o2": 0.0,
    "color": "red",
    "x0": 0.7295329846500888,
    "x0_raw": 0.7295329846500888,
    "A": 1.1380531811734522,
    "r2N": 2.2761063623469044,
    "max_s": 2.0,
    "delta_t": 7.955555555555556,
    "phase": "Deceleration"
  },
  "Malaysia": {
    "x": "2016-04-14 00:00:00",
    "y": 2.0312735994382427,
    "yr": "2021-07-01",
    "c": "Malaysia",
    "o": 174.0,
    "o2": 0.0,
    "color": "red",
    "x0": 0.6404520265844321,
    "x0_raw": 0.6404520265844321,
    "A": 1.1303897094759487,
    "r2N": 196.68780944881507,
    "max_s": 174.0,
    "delta_t": 10.572222222222223,
    "phase": "Deceleration"
  },
  "Mali": {
    "x": "2021-07-01 00:00:00",
    "y": 8.914162905172795,
    "yr": "2021-07-01",
    "c": "Mali",
    "o": 1.0,
    "o2": 0.0,
    "color": "black",
    "x0": 0.820709103782534,
    "x0_raw": 0.820709103782534,
    "A": 0.9999999999999702,
    "r2N": 0.9999999999999702,
    "max_s": 1.0,
    "delta_t": 0.0,
    "phase": "Deactivated"
  },
  "Malta": {
    "x": "2025-08-11 00:00:00",
    "y": 0.9678037020905357,
    "yr": "2021-07-01",
    "c": "Malta",
    "o": 5.0,
    "o2": 0.0,
    "color": "green",
    "x0": 1.283815997290452,
    "x0_raw": 1.283815997290452,
    "A": 3.428452289505077,
    "r2N": 17.142261447525385,
    "max_s": 5.0,
    "delta_t": -8.35,
    "phase": "Acceleration"
  },
  "Mauritius": {
    "x": "2017-09-18 00:00:00",
    "y": 2.7439093328311857,
    "yr": "2021-07-01",
    "c": "Mauritius",
    "o": 9.0,
    "o2": 0.0,
    "color": "red",
    "x0": 0.7391553266266128,
    "x0_raw": 0.7391553266266128,
    "A": 1.0688006835497768,
    "r2N": 9.61920615194799,
    "max_s": 9.0,
    "delta_t": 7.6722222222222225,
    "phase": "Deceleration"
  },
  "Mexico": {
    "x": "2016-12-26 00:00:00",
    "y": 2.3597487717155903,
    "yr": "2021-07-01",
    "c": "Mexico",
    "o": 52.0,
    "o2": 0.0,
    "color": "red",
    "x0": 0.6888908111886967,
    "x0_raw": 0.6888908111886967,
    "A": 1.0965397375427504,
    "r2N": 57.02006635222302,
    "max_s": 52.0,
    "delta_t": 9.15,
    "phase": "Deceleration"
  },
  "Morocco": {
    "x": "2021-07-01 00:00:00",
    "y": 2.862824575808918,
    "yr": "2021-07-01",
    "c": "Morocco",
    "o": 8.0,
    "o2": 0.0,
    "color": "black",
    "x0": 0.6937616041052869,
    "x0_raw": 0.6937616041052869,
    "A": 1.036247849844235,
    "r2N": 8.28998279875388,
    "max_s": 8.0,
    "delta_t": 0.0,
    "phase": "Deactivated"
  },
  "Nepal": {
    "x": "2017-01-12 00:00:00",
    "y": 2.0527673119372936,
    "yr": "2021-07-01",
    "c": "Nepal",
    "o": 3.0,
    "o2": 0.0,
    "color": "red",
    "x0": 0.6921103301286,
    "x0_raw": 0.6921103301286,
    "A": 1.2007485961023239,
    "r2N": 3.6022457883069716,
    "max_s": 3.0,
    "delta_t": 9.055555555555555,
    "phase": "Deceleration"
  },
  "Netherlands": {
    "x": "2016-02-07 00:00:00",
    "y": 1.9367154368878834,
    "yr": "2021-07-01",
    "c": "Netherlands",
    "o": 180.0,
    "o2": 0.0,
    "color": "red",
    "x0": 0.6278405736129055,
    "x0_raw": 0.6278405736129055,
    "A": 1.1353063401284704,
    "r2N": 204.3551412231247,
    "max_s": 180.0,
    "delta_t": 10.944444444444445,
    "phase": "Deceleration"
  },
  "New Zealand": {
    "x": "2015-02-26 00:00:00",
    "y": 2.003486304120509,
    "yr": "2021-07-01",
    "c": "New Zealand",
    "o": 45.0,
    "o2": 0.0,
    "color": "red",
    "x0": 0.5624350985199802,
    "x0_raw": 0.5624350985199802,
    "A": 1.0889918767285116,
    "r2N": 49.00463445278302,
    "max_s": 45.0,
    "delta_t": 12.866666666666667,
    "phase": "Deceleration"
  },
  "Nicaragua": {
    "x": "2021-07-01 00:00:00",
    "y": 8.90995282396443,
    "yr": "2021-07-01",
    "c": "Nicaragua",
    "o": 1.0,
    "o2": 0.0,
    "color": "black",
    "x0": 0.4267652697822612,
    "x0_raw": 0.4267652697822612,
    "A": 1.0000000000000622,
    "r2N": 1.0000000000000622,
    "max_s": 1.0,
    "delta_t": 0.0,
    "phase": "Deactivated"
  },
  "Nigeria": {
    "x": "2017-02-24 00:00:00",
    "y": 2.4988306059469942,
    "yr": "2021-07-01",
    "c": "Nigeria",
    "o": 28.0,
    "o2": 0.0,
    "color": "red",
    "x0": 0.7001831494799015,
    "x0_raw": 0.7001831494799015,
    "A": 1.088717179814164,
    "r2N": 30.48408103479659,
    "max_s": 28.0,
    "delta_t": 8.816666666666666,
    "phase": "Deceleration"
  },
  "North Korea": {
    "x": "2021-07-01 00:00:00",
    "y": 8.915233654905835,
    "yr": "2021-07-01",
    "c": "North Korea",
    "o": 1.0,
    "o2": 0.0,
    "color": "black",
    "x0": 0.8156550940019763,
    "x0_raw": 0.8156550940019763,
    "A": 0.999999999999962,
    "r2N": 0.999999999999962,
    "max_s": 1.0,
    "delta_t": 0.0,
    "phase": "Deactivated"
  },
  "North Macedonia": {
    "x": "2021-07-01 00:00:00",
    "y": 8.905075446563638,
    "yr": "2021-07-01",
    "c": "North Macedonia",
    "o": 1.0,
    "o2": 0.0,
    "color": "black",
    "x0": 0.26010306834053204,
    "x0_raw": 0.26010306834053204,
    "A": 1.000000000000016,
    "r2N": 1.000000000000016,
    "max_s": 1.0,
    "delta_t": 0.0,
    "phase": "Deactivated"
  },
  "Norway": {
    "x": "2016-06-08 00:00:00",
    "y": 1.6906005896525858,
    "yr": "2021-07-01",
    "c": "Norway",
    "o": 106.0,
    "o2": 0.0,
    "color": "red",
    "x0": 0.650862758864857,
    "x0_raw": 0.650862758864857,
    "A": 1.233441642837899,
    "r2N": 130.74481414081728,
    "max_s": 106.0,
    "delta_t": 10.266666666666667,
    "phase": "Deceleration"
  },
  "Oman": {
    "x": "2021-07-01 00:00:00",
    "y": 5.209139080696977,
    "yr": "2021-07-01",
    "c": "Oman",
    "o": 2.0,
    "o2": 0.0,
    "color": "black",
    "x0": 0.8030754660792078,
    "x0_raw": 0.8030754660792078,
    "A": 1.0026388086344855,
    "r2N": 2.005277617268971,
    "max_s": 2.0,
    "delta_t": 0.0,
    "phase": "Deactivated"
  },
  "Pakistan": {
    "x": "2017-05-21 00:00:00",
    "y": 2.313767784187635,
    "yr": "2021-07-01",
    "c": "Pakistan",
    "o": 46.0,
    "o2": 0.0,
    "color": "red",
    "x0": 0.7165102581347678,
    "x0_raw": 0.7165102581347678,
    "A": 1.1286995534748254,
    "r2N": 51.92017945984197,
    "max_s": 46.0,
    "delta_t": 8.338888888888889,
    "phase": "Deceleration"
  },
  "Palestine": {
    "x": "2021-07-01 00:00:00",
    "y": 8.90818566387427,
    "yr": "2021-07-01",
    "c": "Palestine",
    "o": 1.0,
    "o2": 0.0,
    "color": "black",
    "x0": 0.7298024858405076,
    "x0_raw": 0.7298024858405076,
    "A": 0.9999999999999889,
    "r2N": 0.9999999999999889,
    "max_s": 1.0,
    "delta_t": 0.0,
    "phase": "Deactivated"
  },
  "Panama": {
    "x": "2021-07-01 00:00:00",
    "y": 8.920872274734693,
    "yr": "2021-07-01",
    "c": "Panama",
    "o": 1.0,
    "o2": 0.0,
    "color": "black",
    "x0": 0.7398981717762941,
    "x0_raw": 0.7398981717762941,
    "A": 0.9999999999999701,
    "r2N": 0.9999999999999701,
    "max_s": 1.0,
    "delta_t": 0.0,
    "phase": "Deactivated"
  },
  "China": {
    "x": "2016-10-31 00:00:00",
    "y": 2.0116220972898686,
    "yr": "2021-07-01",
    "c": "China",
    "o": 962.0,
    "o2": 0.0,
    "color": "red",
    "x0": 0.6781998575376085,
    "x0_raw": 0.6781998575376085,
    "A": 1.1665102614334228,
    "r2N": 1122.1828714989529,
    "max_s": 962.0,
    "delta_t": 9.46111111111111,
    "phase": "Deceleration"
  },
  "Peru": {
    "x": "2016-12-07 00:00:00",
    "y": 2.442596768639924,
    "yr": "2021-07-01",
    "c": "Peru",
    "o": 14.0,
    "o2": 0.0,
    "color": "red",
    "x0": 0.6853087178424573,
    "x0_raw": 0.6853087178424573,
    "A": 1.0751731384510694,
    "r2N": 15.052423938314972,
    "max_s": 14.0,
    "delta_t": 9.255555555555556,
    "phase": "Deceleration"
  },
  "Philippines": {
    "x": "2015-02-15 00:00:00",
    "y": 1.955035773006328,
    "yr": "2021-07-01",
    "c": "Philippines",
    "o": 38.0,
    "o2": 0.0,
    "color": "red",
    "x0": 0.560485284814565,
    "x0_raw": 0.560485284814565,
    "A": 1.088776870416374,
    "r2N": 41.37352107582221,
    "max_s": 38.0,
    "delta_t": 12.927777777777777,
    "phase": "Deceleration"
  },
  "Poland": {
    "x": "2017-10-24 00:00:00",
    "y": 2.1266373691222595,
    "yr": "2021-07-01",
    "c": "Poland",
    "o": 102.0,
    "o2": 0.0,
    "color": "red",
    "x0": 0.7459255658291908,
    "x0_raw": 0.7459255658291908,
    "A": 1.2309133477464693,
    "r2N": 125.55316147013987,
    "max_s": 102.0,
    "delta_t": 7.472222222222222,
    "phase": "Deceleration"
  },
  "Portugal": {
    "x": "2016-05-17 00:00:00",
    "y": 2.0705637034963518,
    "yr": "2021-07-01",
    "c": "Portugal",
    "o": 107.0,
    "o2": 0.0,
    "color": "red",
    "x0": 0.646669274067774,
    "x0_raw": 0.646669274067774,
    "A": 1.110748523932784,
    "r2N": 118.85009206080788,
    "max_s": 107.0,
    "delta_t": 10.38888888888889,
    "phase": "Deceleration"
  },
  "Qatar": {
    "x": "2017-07-23 00:00:00",
    "y": 2.3644409383200724,
    "yr": "2021-07-01",
    "c": "Qatar",
    "o": 38.0,
    "o2": 0.0,
    "color": "red",
    "x0": 0.728355447016736,
    "x0_raw": 0.728355447016736,
    "A": 1.1318238036876889,
    "r2N": 43.00930454013218,
    "max_s": 38.0,
    "delta_t": 7.988888888888889,
    "phase": "Deceleration"
  },
  "Romania": {
    "x": "2016-04-22 00:00:00",
    "y": 1.9872222639953332,
    "yr": "2021-07-01",
    "c": "Romania",
    "o": 85.0,
    "o2": 0.0,
    "color": "red",
    "x0": 0.6420769949284248,
    "x0_raw": 0.6420769949284248,
    "A": 1.1452373468446035,
    "r2N": 97.3451744817913,
    "max_s": 85.0,
    "delta_t": 10.527777777777779,
    "phase": "Deceleration"
  },
  "Russia": {
    "x": "2018-05-29 00:00:00",
    "y": 2.872189845461633,
    "yr": "2021-07-01",
    "c": "Russia",
    "o": 32.0,
    "o2": 0.0,
    "color": "red",
    "x0": 0.7868567729974925,
    "x0_raw": 0.7868567729974925,
    "A": 1.1055317970251268,
    "r2N": 35.37701750480406,
    "max_s": 32.0,
    "delta_t": 6.266666666666667,
    "phase": "Deceleration"
  },
  "Saudi Arabia": {
    "x": "2017-03-31 00:00:00",
    "y": 2.3961373476249914,
    "yr": "2021-07-01",
    "c": "Saudi Arabia",
    "o": 33.0,
    "o2": 0.0,
    "color": "red",
    "x0": 0.7067513498824096,
    "x0_raw": 0.7067513498824096,
    "A": 1.101070237166634,
    "r2N": 36.33531782649892,
    "max_s": 33.0,
    "delta_t": 8.622222222222222,
    "phase": "Deceleration"
  },
  "Senegal": {
    "x": "2021-07-01 00:00:00",
    "y": 8.907741307583526,
    "yr": "2021-07-01",
    "c": "Senegal",
    "o": 1.0,
    "o2": 0.0,
    "color": "black",
    "x0": 0.3207048272818151,
    "x0_raw": 0.3207048272818151,
    "A": 0.9999999999999994,
    "r2N": 0.9999999999999994,
    "max_s": 1.0,
    "delta_t": 0.0,
    "phase": "Deactivated"
  },
  "Serbia": {
    "x": "2015-09-29 00:00:00",
    "y": 2.3690413628544675,
    "yr": "2021-07-01",
    "c": "Serbia",
    "o": 16.0,
    "o2": 0.0,
    "color": "red",
    "x0": 0.6030346103149945,
    "x0_raw": 0.6030346103149945,
    "A": 1.0517356090170151,
    "r2N": 16.827769744272242,
    "max_s": 16.0,
    "delta_t": 11.672222222222222,
    "phase": "Deceleration"
  },
  "Singapore": {
    "x": "2015-01-04 00:00:00",
    "y": 1.9185439870335645,
    "yr": "2021-07-01",
    "c": "Singapore",
    "o": 80.0,
    "o2": 0.0,
    "color": "red",
    "x0": 0.5524173165808061,
    "x0_raw": 0.5524173165808061,
    "A": 1.0725889225786405,
    "r2N": 85.80711380629124,
    "max_s": 80.0,
    "delta_t": 13.161111111111111,
    "phase": "Deceleration"
  },
  "Slovakia": {
    "x": "2015-08-15 00:00:00",
    "y": 1.8265437749718951,
    "yr": "2021-07-01",
    "c": "Slovakia",
    "o": 17.0,
    "o2": 0.0,
    "color": "red",
    "x0": 0.5947062838561635,
    "x0_raw": 0.5947062838561635,
    "A": 1.1180074992049487,
    "r2N": 19.00612748648413,
    "max_s": 17.0,
    "delta_t": 11.922222222222222,
    "phase": "Deceleration"
  },
  "Slovenia": {
    "x": "2021-07-01 00:00:00",
    "y": 1.9096925488210934,
    "yr": "2021-07-01",
    "c": "Slovenia",
    "o": 32.0,
    "o2": 0.0,
    "color": "black",
    "x0": 0.522523443942254,
    "x0_raw": 0.522523443942254,
    "A": 1.048888680904633,
    "r2N": 33.564437788948254,
    "max_s": 32.0,
    "delta_t": 0.0,
    "phase": "Deactivated"
  },
  "South Africa": {
    "x": "2016-03-31 00:00:00",
    "y": 1.9495779445143777,
    "yr": "2021-07-01",
    "c": "South Africa",
    "o": 97.0,
    "o2": 0.0,
    "color": "red",
    "x0": 0.6378290567740866,
    "x0_raw": 0.6378290567740866,
    "A": 1.1500957058360168,
    "r2N": 111.55928346609363,
    "max_s": 97.0,
    "delta_t": 10.65,
    "phase": "Deceleration"
  },
  "South Korea": {
    "x": "2017-03-12 00:00:00",
    "y": 2.1578181154371125,
    "yr": "2021-07-01",
    "c": "South Korea",
    "o": 85.0,
    "o2": 0.0,
    "color": "red",
    "x0": 0.7032173492340632,
    "x0_raw": 0.7032173492340632,
    "A": 1.148504033463739,
    "r2N": 97.62284284441782,
    "max_s": 85.0,
    "delta_t": 8.727777777777778,
    "phase": "Deceleration"
  },
  "Spain": {
    "x": "2016-12-16 00:00:00",
    "y": 2.040892760607873,
    "yr": "2021-07-01",
    "c": "Spain",
    "o": 477.0,
    "o2": 0.0,
    "color": "red",
    "x0": 0.686962259961323,
    "x0_raw": 0.686962259961323,
    "A": 1.1684434261803154,
    "r2N": 557.3475142880104,
    "max_s": 477.0,
    "delta_t": 9.205555555555556,
    "phase": "Deceleration"
  },
  "Sri Lanka": {
    "x": "2016-07-21 00:00:00",
    "y": 2.2051979590777964,
    "yr": "2021-07-01",
    "c": "Sri Lanka",
    "o": 18.0,
    "o2": 0.0,
    "color": "red",
    "x0": 0.658957358822425,
    "x0_raw": 0.658957358822425,
    "A": 1.1130154210461687,
    "r2N": 20.034277578831038,
    "max_s": 18.0,
    "delta_t": 10.027777777777779,
    "phase": "Deceleration"
  },
  "Sweden": {
    "x": "2016-05-28 00:00:00",
    "y": 2.0536785178125703,
    "yr": "2021-07-01",
    "c": "Sweden",
    "o": 163.0,
    "o2": 0.0,
    "color": "red",
    "x0": 0.6488401712522819,
    "x0_raw": 0.6488401712522819,
    "A": 1.1219208458990855,
    "r2N": 182.87309788155093,
    "max_s": 163.0,
    "delta_t": 10.327777777777778,
    "phase": "Deceleration"
  },
  "Switzerland": {
    "x": "2017-03-02 00:00:00",
    "y": 1.8560530926654706,
    "yr": "2021-07-01",
    "c": "Switzerland",
    "o": 97.0,
    "o2": 0.0,
    "color": "red",
    "x0": 0.7012995335867291,
    "x0_raw": 0.7012995335867291,
    "A": 1.242189295939143,
    "r2N": 120.49236170609687,
    "max_s": 97.0,
    "delta_t": 8.783333333333333,
    "phase": "Deceleration"
  },
  "Taiwan": {
    "x": "2015-10-05 00:00:00",
    "y": 1.9742060406890607,
    "yr": "2021-07-01",
    "c": "Taiwan",
    "o": 119.0,
    "o2": 0.0,
    "color": "red",
    "x0": 0.6041921355514781,
    "x0_raw": 0.6041921355514781,
    "A": 1.1052531912200125,
    "r2N": 131.5251297551815,
    "max_s": 119.0,
    "delta_t": 11.63888888888889,
    "phase": "Deceleration"
  },
  "Tanzania": {
    "x": "2021-07-01 00:00:00",
    "y": 2.350399199856398,
    "yr": "2021-07-01",
    "c": "Tanzania",
    "o": 3.0,
    "o2": 0.0,
    "color": "black",
    "x0": 0.5847175369509287,
    "x0_raw": 0.5847175369509287,
    "A": 0.9782450719156015,
    "r2N": 2.9347352157468043,
    "max_s": 3.0,
    "delta_t": 0.0,
    "phase": "Deactivated"
  },
  "Thailand": {
    "x": "2016-07-12 00:00:00",
    "y": 2.079493680492831,
    "yr": "2021-07-01",
    "c": "Thailand",
    "o": 64.0,
    "o2": 0.0,
    "color": "red",
    "x0": 0.6572702506384523,
    "x0_raw": 0.6572702506384523,
    "A": 1.1125213182302998,
    "r2N": 71.20136436673918,
    "max_s": 64.0,
    "delta_t": 10.077777777777778,
    "phase": "Deceleration"
  },
  "Togo": {
    "x": "2021-07-01 00:00:00",
    "y": 8.946031406780618,
    "yr": "2021-07-01",
    "c": "Togo",
    "o": 1.0,
    "o2": 0.0,
    "color": "black",
    "x0": 0.5631338387735297,
    "x0_raw": 0.5631338387735297,
    "A": 1.0000000000000355,
    "r2N": 1.0000000000000355,
    "max_s": 1.0,
    "delta_t": 0.0,
    "phase": "Deactivated"
  },
  "Trinidad Tobago": {
    "x": "2021-07-01 00:00:00",
    "y": 2.1360272247116594,
    "yr": "2021-07-01",
    "c": "Trinidad Tobago",
    "o": 3.0,
    "o2": 0.0,
    "color": "black",
    "x0": 0.5867033474609288,
    "x0_raw": 0.5867033474609288,
    "A": 1.0436017282342358,
    "r2N": 3.1308051847027074,
    "max_s": 3.0,
    "delta_t": 0.0,
    "phase": "Deactivated"
  },
  "Tunisia": {
    "x": "2018-02-11 00:00:00",
    "y": 2.550381221625227,
    "yr": "2021-07-01",
    "c": "Tunisia",
    "o": 3.0,
    "o2": 0.0,
    "color": "red",
    "x0": 0.7667373312003228,
    "x0_raw": 0.7667373312003228,
    "A": 1.1409587315071186,
    "r2N": 3.422876194521356,
    "max_s": 3.0,
    "delta_t": 6.861111111111111,
    "phase": "Deceleration"
  },
  "Turkey": {
    "x": "2017-04-21 00:00:00",
    "y": 2.496723231085318,
    "yr": "2021-07-01",
    "c": "Turkey",
    "o": 90.0,
    "o2": 0.0,
    "color": "red",
    "x0": 0.7108318515067156,
    "x0_raw": 0.7108318515067156,
    "A": 1.0876594539101017,
    "r2N": 97.88935085190914,
    "max_s": 90.0,
    "delta_t": 8.505555555555556,
    "phase": "Deceleration"
  },
  "U Arab Emirates": {
    "x": "2017-07-22 00:00:00",
    "y": 1.778094429866378,
    "yr": "2021-07-01",
    "c": "U Arab Emirates",
    "o": 44.0,
    "o2": 0.0,
    "color": "red",
    "x0": 0.7280807112043417,
    "x0_raw": 0.7280807112043417,
    "A": 1.322004633937131,
    "r2N": 58.168203893233766,
    "max_s": 44.0,
    "delta_t": 7.9944444444444445,
    "phase": "Deceleration"
  },
  "Uganda": {
    "x": "2021-07-01 00:00:00",
    "y": 8.909398818290017,
    "yr": "2021-07-01",
    "c": "Uganda",
    "o": 1.0,
    "o2": 0.0,
    "color": "black",
    "x0": 0.33080433981601864,
    "x0_raw": 0.33080433981601864,
    "A": 1.000000000000044,
    "r2N": 1.000000000000044,
    "max_s": 1.0,
    "delta_t": 0.0,
    "phase": "Deactivated"
  },
  "Ukraine": {
    "x": "2021-07-01 00:00:00",
    "y": 3.7926626616030776,
    "yr": "2021-07-01",
    "c": "Ukraine",
    "o": 3.0,
    "o2": 0.0,
    "color": "black",
    "x0": 0.7548821551656437,
    "x0_raw": 0.7548821551656437,
    "A": 0.9973977572182515,
    "r2N": 2.9921932716547546,
    "max_s": 3.0,
    "delta_t": 0.0,
    "phase": "Deactivated"
  },
  "Uruguay": {
    "x": "2021-07-01 00:00:00",
    "y": 3.0558325390404395,
    "yr": "2021-07-01",
    "c": "Uruguay",
    "o": 3.0,
    "o2": 0.0,
    "color": "black",
    "x0": 0.41304825594300565,
    "x0_raw": 0.41304825594300565,
    "A": 0.793705797231399,
    "r2N": 2.381117391694197,
    "max_s": 3.0,
    "delta_t": 0.0,
    "phase": "Deactivated"
  },
  "Venezuela": {
    "x": "2017-12-27 00:00:00",
    "y": 1.5203952614365293,
    "yr": "2021-07-01",
    "c": "Venezuela",
    "o": 2.0,
    "o2": 0.0,
    "color": "red",
    "x0": 0.7579903168644619,
    "x0_raw": 0.7579903168644619,
    "A": 1.3636238911595648,
    "r2N": 2.7272477823191297,
    "max_s": 2.0,
    "delta_t": 7.116666666666666,
    "phase": "Deceleration"
  },
  "Vietnam": {
    "x": "2017-03-26 00:00:00",
    "y": 2.411279396220509,
    "yr": "2021-07-01",
    "c": "Vietnam",
    "o": 9.0,
    "o2": 0.0,
    "color": "red",
    "x0": 0.7058996843096509,
    "x0_raw": 0.7058996843096509,
    "A": 1.0989135399115781,
    "r2N": 9.890221859204203,
    "max_s": 9.0,
    "delta_t": 8.65,
    "phase": "Deceleration"
  },
  "Zimbabwe": {
    "x": "2017-09-19 00:00:00",
    "y": 1.7447794532642011,
    "yr": "2021-07-01",
    "c": "Zimbabwe",
    "o": 3.0,
    "o2": 0.0,
    "color": "red",
    "x0": 0.7393639788937267,
    "x0_raw": 0.7393639788937267,
    "A": 1.34804146124639,
    "r2N": 4.04412438373917,
    "max_s": 3.0,
    "delta_t": 7.666666666666667,
    "phase": "Deceleration"
  },
  "USA": {
    "x": "2015-05-02 00:00:00",
    "y": 1.7552231548176467,
    "yr": "2021-07-01",
    "c": "USA",
    "o": 1308.0,
    "o2": 0.0,
    "color": "red",
    "x0": 0.5747626643060901,
    "x0_raw": 0.5747626643060901,
    "A": 1.1284305744675158,
    "r2N": 1475.9871914035107,
    "max_s": 1308.0,
    "delta_t": 12.505555555555556,
    "phase": "Deceleration"
  },
  "UK": {
    "x": "2015-08-02 00:00:00",
    "y": 1.676746593620493,
    "yr": "2021-07-01",
    "c": "UK",
    "o": 703.0,
    "o2": 0.0,
    "color": "red",
    "x0": 0.5921635546666975,
    "x0_raw": 0.5921635546666975,
    "A": 1.170053320201334,
    "r2N": 822.5474841015377,
    "max_s": 703.0,
    "delta_t": 11.994444444444444,
    "phase": "Deceleration"
  }
}