{
  "Australia": {
    "x": "2009-07-01 00:00:00",
    "y": 4.284638765957772,
    "yr": "2009-07-01",
    "c": "Australia",
    "o": 8.0,
    "o2": 0.0,
    "color": "black",
    "x0": 0.06669434934240645,
    "x0_raw": 0.06669434934240645,
    "A": 1.0025734153446646,
    "r2N": 8.020587322757317,
    "max_s": 8.0,
    "delta_t": 0.0,
    "phase": "Deactivated"
  },
  "Brazil": {
    "x": "2009-07-01 00:00:00",
    "y": 8.92915341520533,
    "yr": "2009-07-01",
    "c": "Brazil",
    "o": 1.0,
    "o2": 0.0,
    "color": "black",
    "x0": 0.07828010768430299,
    "x0_raw": 0.07828010768430299,
    "A": 1.0000000000000095,
    "r2N": 1.0000000000000095,
    "max_s": 1.0,
    "delta_t": 0.0,
    "phase": "Deactivated"
  },
  "Canada": {
    "x": "2009-07-01 00:00:00",
    "y": 3.9415275749425924,
    "yr": "2009-07-01",
    "c": "Canada",
    "o": 6.0,
    "o2": 0.0,
    "color": "black",
    "x0": 0.07384494529139603,
    "x0_raw": 0.07384494529139603,
    "A": 1.002388492733582,
    "r2N": 6.014330956401492,
    "max_s": 6.0,
    "delta_t": 0.0,
    "phase": "Deactivated"
  },
  "Czech Republic": {
    "x": "2009-07-01 00:00:00",
    "y": 8.92915341520533,
    "yr": "2009-07-01",
    "c": "Czech Republic",
    "o": 1.0,
    "o2": 0.0,
    "color": "black",
    "x0": 0.07828010768430299,
    "x0_raw": 0.07828010768430299,
    "A": 1.0000000000000095,
    "r2N": 1.0000000000000095,
    "max_s": 1.0,
    "delta_t": 0.0,
    "phase": "Deactivated"
  },
  "Denmark": {
    "x": "2009-07-01 00:00:00",
    "y": 3.9914075011905115,
    "yr": "2009-07-01",
    "c": "Denmark",
    "o": 2.0,
    "o2": 0.0,
    "color": "black",
    "x0": 0.05300701751017008,
    "x0_raw": 0.05300701751017008,
    "A": 1.00179558499686,
    "r2N": 2.00359116999372,
    "max_s": 2.0,
    "delta_t": 0.0,
    "phase": "Deactivated"
  },
  "Fiji": {
    "x": "2009-07-01 00:00:00",
    "y": 8.92915341520533,
    "yr": "2009-07-01",
    "c": "Fiji",
    "o": 1.0,
    "o2": 0.0,
    "color": "black",
    "x0": 0.07828010768430299,
    "x0_raw": 0.07828010768430299,
    "A": 1.0000000000000095,
    "r2N": 1.0000000000000095,
    "max_s": 1.0,
    "delta_t": 0.0,
    "phase": "Deactivated"
  },
  "Finland": {
    "x": "2009-07-01 00:00:00",
    "y": 8.92915341520533,
    "yr": "2009-07-01",
    "c": "Finland",
    "o": 4.0,
    "o2": 0.0,
    "color": "black",
    "x0": 0.07828010768430299,
    "x0_raw": 0.07828010768430299,
    "A": 1.0000000000000095,
    "r2N": 4.000000000000038,
    "max_s": 4.0,
    "delta_t": 0.0,
    "phase": "Deactivated"
  },
  "France": {
    "x": "2009-07-01 00:00:00",
    "y": 3.882382281454694,
    "yr": "2009-07-01",
    "c": "France",
    "o": 2.0,
    "o2": 0.0,
    "color": "black",
    "x0": 0.05031591518364876,
    "x0_raw": 0.05031591518364876,
    "A": 1.002066740072254,
    "r2N": 2.004133480144508,
    "max_s": 2.0,
    "delta_t": 0.0,
    "phase": "Deactivated"
  },
  "Germany": {
    "x": "2009-07-01 00:00:00",
    "y": 5.388416666643614,
    "yr": "2009-07-01",
    "c": "Germany",
    "o": 3.0,
    "o2": 0.0,
    "color": "black",
    "x0": 0.08229745842818742,
    "x0_raw": 0.08229745842818742,
    "A": 0.9996823941210363,
    "r2N": 2.999047182363109,
    "max_s": 3.0,
    "delta_t": 0.0,
    "phase": "Deactivated"
  },
  "Greece": {
    "x": "2009-07-01 00:00:00",
    "y": 8.92915341520533,
    "yr": "2009-07-01",
    "c": "Greece",
    "o": 1.0,
    "o2": 0.0,
    "color": "black",
    "x0": 0.07828010768430299,
    "x0_raw": 0.07828010768430299,
    "A": 1.0000000000000095,
    "r2N": 1.0000000000000095,
    "max_s": 1.0,
    "delta_t": 0.0,
    "phase": "Deactivated"
  },
  "Hungary": {
    "x": "2009-07-01 00:00:00",
    "y": 5.488111724490922,
    "yr": "2009-07-01",
    "c": "Hungary",
    "o": 3.0,
    "o2": 0.0,
    "color": "black",
    "x0": 0.06938827559044453,
    "x0_raw": 0.06938827559044453,
    "A": 1.0000186850334312,
    "r2N": 3.0000560551002935,
    "max_s": 3.0,
    "delta_t": 0.0,
    "phase": "Deactivated"
  },
  "Ireland": {
    "x": "2009-07-01 00:00:00",
    "y": 8.289337675120509,
    "yr": "2009-07-01",
    "c": "Ireland",
    "o": 3.0,
    "o2": 0.0,
    "color": "black",
    "x0": 0.08063397556490412,
    "x0_raw": 0.08063397556490412,
    "A": 1.000000000005087,
    "r2N": 3.000000000015261,
    "max_s": 3.0,
    "delta_t": 0.0,
    "phase": "Deactivated"
  },
  "Italy": {
    "x": "2009-07-01 00:00:00",
    "y": 8.92915341520533,
    "yr": "2009-07-01",
    "c": "Italy",
    "o": 1.0,
    "o2": 0.0,
    "color": "black",
    "x0": 0.07828010768430299,
    "x0_raw": 0.07828010768430299,
    "A": 1.0000000000000095,
    "r2N": 1.0000000000000095,
    "max_s": 1.0,
    "delta_t": 0.0,
    "phase": "Deactivated"
  },
  "Japan": {
    "x": "2009-07-01 00:00:00",
    "y": 8.92915341520533,
    "yr": "2009-07-01",
    "c": "Japan",
    "o": 1.0,
    "o2": 0.0,
    "color": "black",
    "x0": 0.07828010768430299,
    "x0_raw": 0.07828010768430299,
    "A": 1.0000000000000095,
    "r2N": 1.0000000000000095,
    "max_s": 1.0,
    "delta_t": 0.0,
    "phase": "Deactivated"
  },
  "Malaysia": {
    "x": "2009-07-01 00:00:00",
    "y": 8.92915341520533,
    "yr": "2009-07-01",
    "c": "Malaysia",
    "o": 1.0,
    "o2": 0.0,
    "color": "black",
    "x0": 0.07828010768430299,
    "x0_raw": 0.07828010768430299,
    "A": 1.0000000000000095,
    "r2N": 1.0000000000000095,
    "max_s": 1.0,
    "delta_t": 0.0,
    "phase": "Deactivated"
  },
  "Netherlands": {
    "x": "2009-07-01 00:00:00",
    "y": 4.699572876910065,
    "yr": "2009-07-01",
    "c": "Netherlands",
    "o": 2.0,
    "o2": 0.0,
    "color": "black",
    "x0": 0.09093399066458922,
    "x0_raw": 0.09093399066458922,
    "A": 1.0008744118226018,
    "r2N": 2.0017488236452037,
    "max_s": 2.0,
    "delta_t": 0.0,
    "phase": "Deactivated"
  },
  "New Zealand": {
    "x": "2009-07-01 00:00:00",
    "y": 4.175418169660327,
    "yr": "2009-07-01",
    "c": "New Zealand",
    "o": 3.0,
    "o2": 0.0,
    "color": "black",
    "x0": 0.0518147521974965,
    "x0_raw": 0.0518147521974965,
    "A": 1.0013309780769208,
    "r2N": 3.0039929342307623,
    "max_s": 3.0,
    "delta_t": 0.0,
    "phase": "Deactivated"
  },
  "Norway": {
    "x": "2009-07-01 00:00:00",
    "y": 8.92915341520533,
    "yr": "2009-07-01",
    "c": "Norway",
    "o": 1.0,
    "o2": 0.0,
    "color": "black",
    "x0": 0.07828010768430299,
    "x0_raw": 0.07828010768430299,
    "A": 1.0000000000000095,
    "r2N": 1.0000000000000095,
    "max_s": 1.0,
    "delta_t": 0.0,
    "phase": "Deactivated"
  },
  "China": {
    "x": "2009-07-01 00:00:00",
    "y": 8.92915341520533,
    "yr": "2009-07-01",
    "c": "China",
    "o": 1.0,
    "o2": 0.0,
    "color": "black",
    "x0": 0.07828010768430299,
    "x0_raw": 0.07828010768430299,
    "A": 1.0000000000000095,
    "r2N": 1.0000000000000095,
    "max_s": 1.0,
    "delta_t": 0.0,
    "phase": "Deactivated"
  },
  "Philippines": {
    "x": "2009-07-01 00:00:00",
    "y": 8.929222328125704,
    "yr": "2009-07-01",
    "c": "Philippines",
    "o": 1.0,
    "o2": 0.0,
    "color": "black",
    "x0": 0.10858331237648135,
    "x0_raw": 0.10858331237648135,
    "A": 1.0000000000000484,
    "r2N": 1.0000000000000484,
    "max_s": 1.0,
    "delta_t": 0.0,
    "phase": "Deactivated"
  },
  "Singapore": {
    "x": "2009-07-01 00:00:00",
    "y": 8.938238266638331,
    "yr": "2009-07-01",
    "c": "Singapore",
    "o": 1.0,
    "o2": 0.0,
    "color": "black",
    "x0": 0.02272982406832228,
    "x0_raw": 0.02272982406832228,
    "A": 0.9999999999999974,
    "r2N": 0.9999999999999974,
    "max_s": 1.0,
    "delta_t": 0.0,
    "phase": "Deactivated"
  },
  "South Africa": {
    "x": "2009-07-01 00:00:00",
    "y": 8.92915341520533,
    "yr": "2009-07-01",
    "c": "South Africa",
    "o": 1.0,
    "o2": 0.0,
    "color": "black",
    "x0": 0.07828010768430299,
    "x0_raw": 0.07828010768430299,
    "A": 1.0000000000000095,
    "r2N": 1.0000000000000095,
    "max_s": 1.0,
    "delta_t": 0.0,
    "phase": "Deactivated"
  },
  "South Korea": {
    "x": "2009-07-01 00:00:00",
    "y": 4.69961495317846,
    "yr": "2009-07-01",
    "c": "South Korea",
    "o": 2.0,
    "o2": 0.0,
    "color": "black",
    "x0": 0.06568076275309202,
    "x0_raw": 0.06568076275309202,
    "A": 1.000850026872789,
    "r2N": 2.001700053745578,
    "max_s": 2.0,
    "delta_t": 0.0,
    "phase": "Deactivated"
  },
  "Switzerland": {
    "x": "2009-07-01 00:00:00",
    "y": 4.22630833350074,
    "yr": "2009-07-01",
    "c": "Switzerland",
    "o": 2.0,
    "o2": 0.0,
    "color": "black",
    "x0": 0.05813261683757008,
    "x0_raw": 0.05813261683757008,
    "A": 1.0013722493735102,
    "r2N": 2.0027444987470204,
    "max_s": 2.0,
    "delta_t": 0.0,
    "phase": "Deactivated"
  },
  "U Arab Emirates": {
    "x": "2009-07-01 00:00:00",
    "y": 8.92915341520533,
    "yr": "2009-07-01",
    "c": "U Arab Emirates",
    "o": 1.0,
    "o2": 0.0,
    "color": "black",
    "x0": 0.07828010768430299,
    "x0_raw": 0.07828010768430299,
    "A": 1.0000000000000095,
    "r2N": 1.0000000000000095,
    "max_s": 1.0,
    "delta_t": 0.0,
    "phase": "Deactivated"
  },
  "USA": {
    "x": "2009-07-01 00:00:00",
    "y": 3.932120665794919,
    "yr": "2009-07-01",
    "c": "USA",
    "o": 50.0,
    "o2": 0.0,
    "color": "black",
    "x0": 0.06212537690228774,
    "x0_raw": 0.06212537690228774,
    "A": 1.0020740091704843,
    "r2N": 50.103700458524216,
    "max_s": 50.0,
    "delta_t": 0.0,
    "phase": "Deactivated"
  },
  "UK": {
    "x": "2009-07-01 00:00:00",
    "y": 3.87373023753256,
    "yr": "2009-07-01",
    "c": "UK",
    "o": 40.0,
    "o2": 0.0,
    "color": "black",
    "x0": 0.05988051523848161,
    "x0_raw": 0.05988051523848161,
    "A": 1.0025753942176874,
    "r2N": 40.10301576870749,
    "max_s": 40.0,
    "delta_t": 0.0,
    "phase": "Deactivated"
  }
}